Workbook

Sheet Executive_Dashboard
B2: 交易所资金流向与业务风控全局决策看板 (Executive Funds Flow & Risk Monitor) | P2: 看板数据层 · 月度出入金与净流入序列 (Monthly Flow Aggregation)
B4: 监控周期: 2024Q4 - 2025Q4 | 质检状态: 🟢 核心规则全部合规 (17/17 QA Checks Passed) | 预警等级: ⚠️ 发现冻结用户出金与网络挂起风险 | P4: 月份 (Month) | Q4: 充值入金 (Deposit) | R4: 提现出金 (Withdrawal) | S4: 净沉淀额 (Net Inflow)
P5: =DATE(2024, 12, 1) -> 45627 | Q5: =SUMIFS(fiat_transactions!$E$2:$E$26, fiat_transactions!$D$2:$D$26, "USD", fiat_transactions!$C$2:$C$26, "deposit", fiat_transactions!$H$2:$H$26, "completed", fiat_transactions!$I$2:$I$26, ">="&$P5, fiat_transactions!$I$2:$I$26, "<"&EDATE($P5, 1)) + SUMIFS(crypto_transactions!$F$2:$F$26, crypto_transactions!$D$2:$D$26, "USDT", crypto_transactions!$C$2:$C$26, "deposit", crypto_transactions!$J$2:$J$26, "completed", crypto_transactions!$L$2:$L$26, ">="&$P5, crypto_transactions!$L$2:$L$26, "<"&EDATE($P5, 1)) -> 300 | R5: =SUMIFS(fiat_transactions!$E$2:$E$26, fiat_transactions!$D$2:$D$26, "USD", fiat_transactions!$C$2:$C$26, "withdrawal", fiat_transactions!$H$2:$H$26, "completed", fiat_transactions!$I$2:$I$26, ">="&$P5, fiat_transactions!$I$2:$I$26, "<"&EDATE($P5, 1)) + SUMIFS(crypto_transactions!$F$2:$F$26, crypto_transactions!$D$2:$D$26, "USDT", crypto_transactions!$C$2:$C$26, "withdrawal", crypto_transactions!$J$2:$J$26, "completed", crypto_transactions!$L$2:$L$26, ">="&$P5, crypto_transactions!$L$2:$L$26, "<"&EDATE($P5, 1)) -> 0 | S5: =Q5-R5 -> 300
B6: 法币核心总流水 (USD GMV) | E6: 链上核心总流水 (USDT GMV) | I6: 全局订单履约成功率 | L6: 法币核心净沉淀 (USD Net Inflow) | P6: =DATE(2025, 1, 1) -> 45658 | Q6: =SUMIFS(fiat_transactions!$E$2:$E$26, fiat_transactions!$D$2:$D$26, "USD", fiat_transactions!$C$2:$C$26, "deposit", fiat_transactions!$H$2:$H$26, "completed", fiat_transactions!$I$2:$I$26, ">="&$P6, fiat_transactions!$I$2:$I$26, "<"&EDATE($P6, 1)) + SUMIFS(crypto_transactions!$F$2:$F$26, crypto_transactions!$D$2:$D$26, "USDT", crypto_transactions!$C$2:$C$26, "deposit", crypto_transactions!$J$2:$J$26, "completed", crypto_transactions!$L$2:$L$26, ">="&$P6, crypto_transactions!$L$2:$L$26, "<"&EDATE($P6, 1)) -> 53500 | R6: =SUMIFS(fiat_transactions!$E$2:$E$26, fiat_transactions!$D$2:$D$26, "USD", fiat_transactions!$C$2:$C$26, "withdrawal", fiat_transactions!$H$2:$H$26, "completed", fiat_transactions!$I$2:$I$26, ">="&$P6, fiat_transactions!$I$2:$I$26, "<"&EDATE($P6, 1)) + SUMIFS(crypto_transactions!$F$2:$F$26, crypto_transactions!$D$2:$D$26, "USDT", crypto_transactions!$C$2:$C$26, "withdrawal", crypto_transactions!$J$2:$J$26, "completed", crypto_transactions!$L$2:$L$26, ">="&$P6, crypto_transactions!$L$2:$L$26, "<"&EDATE($P6, 1)) -> 0 | S6: =Q6-R6 -> 53500
B7: =SUMIFS(fiat_transactions!E:E, fiat_transactions!D:D, "USD", fiat_transactions!H:H, "completed") -> 104270 | E7: ="13,000 USDT" -> 13,000 USDT | I7: =(COUNTIF(fiat_transactions!H:H, "completed") + COUNTIF(crypto_transactions!J:J, "completed")) / ((COUNTA(fiat_transactions!A:A)-1) + (COUNTA(crypto_transactions!A:A)-1)) -> 0.86 | L7: =SUMIFS(fiat_transactions!E:E, fiat_transactions!D:D, "USD", fiat_transactions!C:C, "deposit", fiat_transactions!H:H, "completed") - SUMIFS(fiat_transactions!E:E, fiat_transactions!D:D, "USD", fiat_transactions!C:C, "withdrawal", fiat_transactions!H:H, "completed") -> 47730 | P7: =DATE(2025, 2, 1) -> 45689 | Q7: =SUMIFS(fiat_transactions!$E$2:$E$26, fiat_transactions!$D$2:$D$26, "USD", fiat_transactions!$C$2:$C$26, "deposit", fiat_transactions!$H$2:$H$26, "completed", fiat_transactions!$I$2:$I$26, ">="&$P7, fiat_transactions!$I$2:$I$26, "<"&EDATE($P7, 1)) + SUMIFS(crypto_transactions!$F$2:$F$26, crypto_transactions!$D$2:$D$26, "USDT", crypto_transactions!$C$2:$C$26, "deposit", crypto_transactions!$J$2:$J$26, "completed", crypto_transactions!$L$2:$L$26, ">="&$P7, crypto_transactions!$L$2:$L$26, "<"&EDATE($P7, 1)) -> 400 | R7: =SUMIFS(fiat_transactions!$E$2:$E$26, fiat_transactions!$D$2:$D$26, "USD", fiat_transactions!$C$2:$C$26, "withdrawal", fiat_transactions!$H$2:$H$26, "completed", fiat_transactions!$I$2:$I$26, ">="&$P7, fiat_transactions!$I$2:$I$26, "<"&EDATE($P7, 1)) + SUMIFS(crypto_transactions!$F$2:$F$26, crypto_transactions!$D$2:$D$26, "USDT", crypto_transactions!$C$2:$C$26, "withdrawal", crypto_transactions!$J$2:$J$26, "completed", crypto_transactions!$L$2:$L$26, ">="&$P7, crypto_transactions!$L$2:$L$26, "<"&EDATE($P7, 1)) -> 12500 | S7: =Q7-R7 -> -12100
B8: ="已完成 9 笔 USD / 全币种 21 笔" -> 已完成 9 笔 USD / 全币种 21 笔 | E8: ="已完成 15 笔 USDT / 覆盖 4 大公链" -> 已完成 15 笔 USDT / 覆盖 4 大公链 | I8: ="43 笔成功 / 7 笔异常或挂起" -> 43 笔成功 / 7 笔异常或挂起 | L8: 充值 $76,000 | 提现 $28,270 | P8: =DATE(2025, 3, 1) -> 45717 | Q8: =SUMIFS(fiat_transactions!$E$2:$E$26, fiat_transactions!$D$2:$D$26, "USD", fiat_transactions!$C$2:$C$26, "deposit", fiat_transactions!$H$2:$H$26, "completed", fiat_transactions!$I$2:$I$26, ">="&$P8, fiat_transactions!$I$2:$I$26, "<"&EDATE($P8, 1)) + SUMIFS(crypto_transactions!$F$2:$F$26, crypto_transactions!$D$2:$D$26, "USDT", crypto_transactions!$C$2:$C$26, "deposit", crypto_transactions!$J$2:$J$26, "completed", crypto_transactions!$L$2:$L$26, ">="&$P8, crypto_transactions!$L$2:$L$26, "<"&EDATE($P8, 1)) -> 1000 | R8: =SUMIFS(fiat_transactions!$E$2:$E$26, fiat_transactions!$D$2:$D$26, "USD", fiat_transactions!$C$2:$C$26, "withdrawal", fiat_transactions!$H$2:$H$26, "completed", fiat_transactions!$I$2:$I$26, ">="&$P8, fiat_transactions!$I$2:$I$26, "<"&EDATE($P8, 1)) + SUMIFS(crypto_transactions!$F$2:$F$26, crypto_transactions!$D$2:$D$26, "USDT", crypto_transactions!$C$2:$C$26, "withdrawal", crypto_transactions!$J$2:$J$26, "completed", crypto_transactions!$L$2:$L$26, ">="&$P8, crypto_transactions!$L$2:$L$26, "<"&EDATE($P8, 1)) -> 600 | S8: =Q8-R8 -> 400
B9: ="通道手续费创收: $" & TEXT(SUM(fiat_transactions!F2:F26), "0.00") -> 通道手续费创收: $150.50 | E9: ="链上手续费创收: " & TEXT(SUMIFS(crypto_transactions!G2:G26, crypto_transactions!D2:D26, "USDT"), "0.00") & " USDT" -> 链上手续费创收: 10.90 USDT | I9: ="质检合规率: 100% (17/17 项规则)" -> 质检合规率: 100% (17/17 项规则) | L9: ="USDT 净沉淀: +3,000.00 USDT" -> USDT 净沉淀: +3,000.00 USDT | P9: =DATE(2025, 4, 1) -> 45748 | Q9: =SUMIFS(fiat_transactions!$E$2:$E$26, fiat_transactions!$D$2:$D$26, "USD", fiat_transactions!$C$2:$C$26, "deposit", fiat_transactions!$H$2:$H$26, "completed", fiat_transactions!$I$2:$I$26, ">="&$P9, fiat_transactions!$I$2:$I$26, "<"&EDATE($P9, 1)) + SUMIFS(crypto_transactions!$F$2:$F$26, crypto_transactions!$D$2:$D$26, "USDT", crypto_transactions!$C$2:$C$26, "deposit", crypto_transactions!$J$2:$J$26, "completed", crypto_transactions!$L$2:$L$26, ">="&$P9, crypto_transactions!$L$2:$L$26, "<"&EDATE($P9, 1)) -> 700 | R9: =SUMIFS(fiat_transactions!$E$2:$E$26, fiat_transactions!$D$2:$D$26, "USD", fiat_transactions!$C$2:$C$26, "withdrawal", fiat_transactions!$H$2:$H$26, "completed", fiat_transactions!$I$2:$I$26, ">="&$P9, fiat_transactions!$I$2:$I$26, "<"&EDATE($P9, 1)) + SUMIFS(crypto_transactions!$F$2:$F$26, crypto_transactions!$D$2:$D$26, "USDT", crypto_transactions!$C$2:$C$26, "withdrawal", crypto_transactions!$J$2:$J$26, "completed", crypto_transactions!$L$2:$L$26, ">="&$P9, crypto_transactions!$L$2:$L$26, "<"&EDATE($P9, 1)) -> 1950 | S9: =Q9-R9 -> -1250
P10: =DATE(2025, 5, 1) -> 45778 | Q10: =SUMIFS(fiat_transactions!$E$2:$E$26, fiat_transactions!$D$2:$D$26, "USD", fiat_transactions!$C$2:$C$26, "deposit", fiat_transactions!$H$2:$H$26, "completed", fiat_transactions!$I$2:$I$26, ">="&$P10, fiat_transactions!$I$2:$I$26, "<"&EDATE($P10, 1)) + SUMIFS(crypto_transactions!$F$2:$F$26, crypto_transactions!$D$2:$D$26, "USDT", crypto_transactions!$C$2:$C$26, "deposit", crypto_transactions!$J$2:$J$26, "completed", crypto_transactions!$L$2:$L$26, ">="&$P10, crypto_transactions!$L$2:$L$26, "<"&EDATE($P10, 1)) -> 0 | R10: =SUMIFS(fiat_transactions!$E$2:$E$26, fiat_transactions!$D$2:$D$26, "USD", fiat_transactions!$C$2:$C$26, "withdrawal", fiat_transactions!$H$2:$H$26, "completed", fiat_transactions!$I$2:$I$26, ">="&$P10, fiat_transactions!$I$2:$I$26, "<"&EDATE($P10, 1)) + SUMIFS(crypto_transactions!$F$2:$F$26, crypto_transactions!$D$2:$D$26, "USDT", crypto_transactions!$C$2:$C$26, "withdrawal", crypto_transactions!$J$2:$J$26, "completed", crypto_transactions!$L$2:$L$26, ">="&$P10, crypto_transactions!$L$2:$L$26, "<"&EDATE($P10, 1)) -> 0 | S10: =Q10-R10 -> 0
B11: 💵 多币种出入金与流动性分析 (Fiat & Crypto Liquidity Net Flow) | I11: ⚡ 结算通道与公链网络稳定性监控 (Channel & Network Reliability) | P11: =DATE(2025, 6, 1) -> 45809 | Q11: =SUMIFS(fiat_transactions!$E$2:$E$26, fiat_transactions!$D$2:$D$26, "USD", fiat_transactions!$C$2:$C$26, "deposit", fiat_transactions!$H$2:$H$26, "completed", fiat_transactions!$I$2:$I$26, ">="&$P11, fiat_transactions!$I$2:$I$26, "<"&EDATE($P11, 1)) + SUMIFS(crypto_transactions!$F$2:$F$26, crypto_transactions!$D$2:$D$26, "USDT", crypto_transactions!$C$2:$C$26, "deposit", crypto_transactions!$J$2:$J$26, "completed", crypto_transactions!$L$2:$L$26, ">="&$P11, crypto_transactions!$L$2:$L$26, "<"&EDATE($P11, 1)) -> 25000 | R11: =SUMIFS(fiat_transactions!$E$2:$E$26, fiat_transactions!$D$2:$D$26, "USD", fiat_transactions!$C$2:$C$26, "withdrawal", fiat_transactions!$H$2:$H$26, "completed", fiat_transactions!$I$2:$I$26, ">="&$P11, fiat_transactions!$I$2:$I$26, "<"&EDATE($P11, 1)) + SUMIFS(crypto_transactions!$F$2:$F$26, crypto_transactions!$D$2:$D$26, "USDT", crypto_transactions!$C$2:$C$26, "withdrawal", crypto_transactions!$J$2:$J$26, "completed", crypto_transactions!$L$2:$L$26, ">="&$P11, crypto_transactions!$L$2:$L$26, "<"&EDATE($P11, 1)) -> 5000 | S11: =Q11-R11 -> 20000
B12: 资产 / 币种 | C12: 资产类别 | D12: 充值入金 (Deposit) | E12: 提现出金 (Withdrawal) | F12: 净流动量 (Net Flow) | G12: 净流动状态 | I12: 通道 / 网络 | J12: 业务类型 | K12: 总订单数 | L12: 成功履约率 | M12: 异常/挂起率 | N12: 手续费创收 | P12: =DATE(2025, 7, 1) -> 45839 | Q12: =SUMIFS(fiat_transactions!$E$2:$E$26, fiat_transactions!$D$2:$D$26, "USD", fiat_transactions!$C$2:$C$26, "deposit", fiat_transactions!$H$2:$H$26, "completed", fiat_transactions!$I$2:$I$26, ">="&$P12, fiat_transactions!$I$2:$I$26, "<"&EDATE($P12, 1)) + SUMIFS(crypto_transactions!$F$2:$F$26, crypto_transactions!$D$2:$D$26, "USDT", crypto_transactions!$C$2:$C$26, "deposit", crypto_transactions!$J$2:$J$26, "completed", crypto_transactions!$L$2:$L$26, ">="&$P12, crypto_transactions!$L$2:$L$26, "<"&EDATE($P12, 1)) -> 0 | R12: =SUMIFS(fiat_transactions!$E$2:$E$26, fiat_transactions!$D$2:$D$26, "USD", fiat_transactions!$C$2:$C$26, "withdrawal", fiat_transactions!$H$2:$H$26, "completed", fiat_transactions!$I$2:$I$26, ">="&$P12, fiat_transactions!$I$2:$I$26, "<"&EDATE($P12, 1)) + SUMIFS(crypto_transactions!$F$2:$F$26, crypto_transactions!$D$2:$D$26, "USDT", crypto_transactions!$C$2:$C$26, "withdrawal", crypto_transactions!$J$2:$J$26, "completed", crypto_transactions!$L$2:$L$26, ">="&$P12, crypto_transactions!$L$2:$L$26, "<"&EDATE($P12, 1)) -> 0 | S12: =Q12-R12 -> 0
B13: USD | C13: 法币 (Fiat) | D13: =SUMIFS(fiat_transactions!$E$2:$E$26, fiat_transactions!$D$2:$D$26, "USD", fiat_transactions!$C$2:$C$26, "deposit", fiat_transactions!$H$2:$H$26, "completed") -> 76000 | E13: =SUMIFS(fiat_transactions!$E$2:$E$26, fiat_transactions!$D$2:$D$26, "USD", fiat_transactions!$C$2:$C$26, "withdrawal", fiat_transactions!$H$2:$H$26, "completed") -> 28270 | F13: =D13-E13 -> 47730 | G13: =IF(F13>0,"🟢 净流入",IF(F13=0,"⚪ 持平","🔴 净流出")) -> 🟢 净流入 | I13: wire_transfer | J13: 法币大额电汇 | K13: =COUNTIF(fiat_transactions!G2:G26, "wire_transfer") -> 6 | L13: =COUNTIFS(fiat_transactions!G2:G26, "wire_transfer", fiat_transactions!H2:H26, "completed") / K13 -> 0.83333333 | M13: =1 - L13 -> 0.16666667 | N13: =SUMIF(fiat_transactions!G2:G26, "wire_transfer", fiat_transactions!F2:F26) -> 120 | P13: =DATE(2025, 8, 1) -> 45870 | Q13: =SUMIFS(fiat_transactions!$E$2:$E$26, fiat_transactions!$D$2:$D$26, "USD", fiat_transactions!$C$2:$C$26, "deposit", fiat_transactions!$H$2:$H$26, "completed", fiat_transactions!$I$2:$I$26, ">="&$P13, fiat_transactions!$I$2:$I$26, "<"&EDATE($P13, 1)) + SUMIFS(crypto_transactions!$F$2:$F$26, crypto_transactions!$D$2:$D$26, "USDT", crypto_transactions!$C$2:$C$26, "deposit", crypto_transactions!$J$2:$J$26, "completed", crypto_transactions!$L$2:$L$26, ">="&$P13, crypto_transactions!$L$2:$L$26, "<"&EDATE($P13, 1)) -> 600 | R13: =SUMIFS(fiat_transactions!$E$2:$E$26, fiat_transactions!$D$2:$D$26, "USD", fiat_transactions!$C$2:$C$26, "withdrawal", fiat_transactions!$H$2:$H$26, "completed", fiat_transactions!$I$2:$I$26, ">="&$P13, fiat_transactions!$I$2:$I$26, "<"&EDATE($P13, 1)) + SUMIFS(crypto_transactions!$F$2:$F$26, crypto_transactions!$D$2:$D$26, "USDT", crypto_transactions!$C$2:$C$26, "withdrawal", crypto_transactions!$J$2:$J$26, "completed", crypto_transactions!$L$2:$L$26, ">="&$P13, crypto_transactions!$L$2:$L$26, "<"&EDATE($P13, 1)) -> 0 | S13: =Q13-R13 -> 600
B14: EUR | C14: 法币 (Fiat) | D14: =SUMIFS(fiat_transactions!$E$2:$E$26, fiat_transactions!$D$2:$D$26, "EUR", fiat_transactions!$C$2:$C$26, "deposit", fiat_transactions!$H$2:$H$26, "completed") -> 9500 | E14: =SUMIFS(fiat_transactions!$E$2:$E$26, fiat_transactions!$D$2:$D$26, "EUR", fiat_transactions!$C$2:$C$26, "withdrawal", fiat_transactions!$H$2:$H$26, "completed") -> 500 | F14: =D14-E14 -> 9000 | G14: =IF(F14>0,"🟢 净流入",IF(F14=0,"⚪ 持平","🔴 净流出")) -> 🟢 净流入 | I14: ach | J14: 法币小额清算 | K14: =COUNTIF(fiat_transactions!G2:G26, "ach") -> 5 | L14: =COUNTIFS(fiat_transactions!G2:G26, "ach", fiat_transactions!H2:H26, "completed") / K14 -> 0.8 | M14: =1 - L14 -> 0.2 | N14: =SUMIF(fiat_transactions!G2:G26, "ach", fiat_transactions!F2:F26) -> 7 | P14: =DATE(2025, 9, 1) -> 45901 | Q14: =SUMIFS(fiat_transactions!$E$2:$E$26, fiat_transactions!$D$2:$D$26, "USD", fiat_transactions!$C$2:$C$26, "deposit", fiat_transactions!$H$2:$H$26, "completed", fiat_transactions!$I$2:$I$26, ">="&$P14, fiat_transactions!$I$2:$I$26, "<"&EDATE($P14, 1)) + SUMIFS(crypto_transactions!$F$2:$F$26, crypto_transactions!$D$2:$D$26, "USDT", crypto_transactions!$C$2:$C$26, "deposit", crypto_transactions!$J$2:$J$26, "completed", crypto_transactions!$L$2:$L$26, ">="&$P14, crypto_transactions!$L$2:$L$26, "<"&EDATE($P14, 1)) -> 0 | R14: =SUMIFS(fiat_transactions!$E$2:$E$26, fiat_transactions!$D$2:$D$26, "USD", fiat_transactions!$C$2:$C$26, "withdrawal", fiat_transactions!$H$2:$H$26, "completed", fiat_transactions!$I$2:$I$26, ">="&$P14, fiat_transactions!$I$2:$I$26, "<"&EDATE($P14, 1)) + SUMIFS(crypto_transactions!$F$2:$F$26, crypto_transactions!$D$2:$D$26, "USDT", crypto_transactions!$C$2:$C$26, "withdrawal", crypto_transactions!$J$2:$J$26, "completed", crypto_transactions!$L$2:$L$26, ">="&$P14, crypto_transactions!$L$2:$L$26, "<"&EDATE($P14, 1)) -> 11100 | S14: =Q14-R14 -> -11100
B15: GBP | C15: 法币 (Fiat) | D15: =SUMIFS(fiat_transactions!$E$2:$E$26, fiat_transactions!$D$2:$D$26, "GBP", fiat_transactions!$C$2:$C$26, "deposit", fiat_transactions!$H$2:$H$26, "completed") -> 3000 | E15: =SUMIFS(fiat_transactions!$E$2:$E$26, fiat_transactions!$D$2:$D$26, "GBP", fiat_transactions!$C$2:$C$26, "withdrawal", fiat_transactions!$H$2:$H$26, "completed") -> 2000 | F15: =D15-E15 -> 1000 | G15: =IF(F15>0,"🟢 净流入",IF(F15=0,"⚪ 持平","🔴 净流出")) -> 🟢 净流入 | I15: sepa_instant | J15: 欧洲即时汇款 | K15: =COUNTIF(fiat_transactions!G2:G26, "sepa_instant") -> 4 | L15: =COUNTIFS(fiat_transactions!G2:G26, "sepa_instant", fiat_transactions!H2:H26, "completed") / K15 -> 0.75 | M15: =1 - L15 -> 0.25 | N15: =SUMIF(fiat_transactions!G2:G26, "sepa_instant", fiat_transactions!F2:F26) -> 3 | P15: =DATE(2025, 10, 1) -> 45931 | Q15: =SUMIFS(fiat_transactions!$E$2:$E$26, fiat_transactions!$D$2:$D$26, "USD", fiat_transactions!$C$2:$C$26, "deposit", fiat_transactions!$H$2:$H$26, "completed", fiat_transactions!$I$2:$I$26, ">="&$P15, fiat_transactions!$I$2:$I$26, "<"&EDATE($P15, 1)) + SUMIFS(crypto_transactions!$F$2:$F$26, crypto_transactions!$D$2:$D$26, "USDT", crypto_transactions!$C$2:$C$26, "deposit", crypto_transactions!$J$2:$J$26, "completed", crypto_transactions!$L$2:$L$26, ">="&$P15, crypto_transactions!$L$2:$L$26, "<"&EDATE($P15, 1)) -> 1000 | R15: =SUMIFS(fiat_transactions!$E$2:$E$26, fiat_transactions!$D$2:$D$26, "USD", fiat_transactions!$C$2:$C$26, "withdrawal", fiat_transactions!$H$2:$H$26, "completed", fiat_transactions!$I$2:$I$26, ">="&$P15, fiat_transactions!$I$2:$I$26, "<"&EDATE($P15, 1)) + SUMIFS(crypto_transactions!$F$2:$F$26, crypto_transactions!$D$2:$D$26, "USDT", crypto_transactions!$C$2:$C$26, "withdrawal", crypto_transactions!$J$2:$J$26, "completed", crypto_transactions!$L$2:$L$26, ">="&$P15, crypto_transactions!$L$2:$L$26, "<"&EDATE($P15, 1)) -> 20 | S15: =Q15-R15 -> 980
B16: BRL | C16: 法币 (Fiat) | D16: =SUMIFS(fiat_transactions!$E$2:$E$26, fiat_transactions!$D$2:$D$26, "BRL", fiat_transactions!$C$2:$C$26, "deposit", fiat_transactions!$H$2:$H$26, "completed") -> 2500 | E16: =SUMIFS(fiat_transactions!$E$2:$E$26, fiat_transactions!$D$2:$D$26, "BRL", fiat_transactions!$C$2:$C$26, "withdrawal", fiat_transactions!$H$2:$H$26, "completed") -> 2500 | F16: =D16-E16 -> 0 | G16: =IF(F16>0,"🟢 净流入",IF(F16=0,"⚪ 持平","🔴 净流出")) -> ⚪ 持平 | I16: faster_payments | J16: 英国极速到账 | K16: =COUNTIF(fiat_transactions!G2:G26, "faster_payments") -> 4 | L16: =COUNTIFS(fiat_transactions!G2:G26, "faster_payments", fiat_transactions!H2:H26, "completed") / K16 -> 0.75 | M16: =1 - L16 -> 0.25 | N16: =SUMIF(fiat_transactions!G2:G26, "faster_payments", fiat_transactions!F2:F26) -> 2 | P16: =DATE(2025, 11, 1) -> 45962 | Q16: =SUMIFS(fiat_transactions!$E$2:$E$26, fiat_transactions!$D$2:$D$26, "USD", fiat_transactions!$C$2:$C$26, "deposit", fiat_transactions!$H$2:$H$26, "completed", fiat_transactions!$I$2:$I$26, ">="&$P16, fiat_transactions!$I$2:$I$26, "<"&EDATE($P16, 1)) + SUMIFS(crypto_transactions!$F$2:$F$26, crypto_transactions!$D$2:$D$26, "USDT", crypto_transactions!$C$2:$C$26, "deposit", crypto_transactions!$J$2:$J$26, "completed", crypto_transactions!$L$2:$L$26, ">="&$P16, crypto_transactions!$L$2:$L$26, "<"&EDATE($P16, 1)) -> 0 | R16: =SUMIFS(fiat_transactions!$E$2:$E$26, fiat_transactions!$D$2:$D$26, "USD", fiat_transactions!$C$2:$C$26, "withdrawal", fiat_transactions!$H$2:$H$26, "completed", fiat_transactions!$I$2:$I$26, ">="&$P16, fiat_transactions!$I$2:$I$26, "<"&EDATE($P16, 1)) + SUMIFS(crypto_transactions!$F$2:$F$26, crypto_transactions!$D$2:$D$26, "USDT", crypto_transactions!$C$2:$C$26, "withdrawal", crypto_transactions!$J$2:$J$26, "completed", crypto_transactions!$L$2:$L$26, ">="&$P16, crypto_transactions!$L$2:$L$26, "<"&EDATE($P16, 1)) -> 300 | S16: =Q16-R16 -> -300
B17: TRY | C17: 法币 (Fiat) | D17: =SUMIFS(fiat_transactions!$E$2:$E$26, fiat_transactions!$D$2:$D$26, "TRY", fiat_transactions!$C$2:$C$26, "deposit", fiat_transactions!$H$2:$H$26, "completed") -> 15000 | E17: =SUMIFS(fiat_transactions!$E$2:$E$26, fiat_transactions!$D$2:$D$26, "TRY", fiat_transactions!$C$2:$C$26, "withdrawal", fiat_transactions!$H$2:$H$26, "completed") -> 6000 | F17: =D17-E17 -> 9000 | G17: =IF(F17>0,"🟢 净流入",IF(F17=0,"⚪ 持平","🔴 净流出")) -> 🟢 净流入 | I17: TRON | J17: 链上 TRC-20 | K17: =COUNTIF(crypto_transactions!E2:E26, "TRON") -> 11 | L17: =COUNTIFS(crypto_transactions!E2:E26, "TRON", crypto_transactions!J2:J26, "completed") / K17 -> 1 | M17: =1 - L17 -> 0 | N17: =SUMIF(crypto_transactions!E2:E26, "TRON", crypto_transactions!G2:G26) -> 4 | P17: =DATE(2025, 12, 1) -> 45992 | Q17: =SUMIFS(fiat_transactions!$E$2:$E$26, fiat_transactions!$D$2:$D$26, "USD", fiat_transactions!$C$2:$C$26, "deposit", fiat_transactions!$H$2:$H$26, "completed", fiat_transactions!$I$2:$I$26, ">="&$P17, fiat_transactions!$I$2:$I$26, "<"&EDATE($P17, 1)) + SUMIFS(crypto_transactions!$F$2:$F$26, crypto_transactions!$D$2:$D$26, "USDT", crypto_transactions!$C$2:$C$26, "deposit", crypto_transactions!$J$2:$J$26, "completed", crypto_transactions!$L$2:$L$26, ">="&$P17, crypto_transactions!$L$2:$L$26, "<"&EDATE($P17, 1)) -> 1000 | R17: =SUMIFS(fiat_transactions!$E$2:$E$26, fiat_transactions!$D$2:$D$26, "USD", fiat_transactions!$C$2:$C$26, "withdrawal", fiat_transactions!$H$2:$H$26, "completed", fiat_transactions!$I$2:$I$26, ">="&$P17, fiat_transactions!$I$2:$I$26, "<"&EDATE($P17, 1)) + SUMIFS(crypto_transactions!$F$2:$F$26, crypto_transactions!$D$2:$D$26, "USDT", crypto_transactions!$C$2:$C$26, "withdrawal", crypto_transactions!$J$2:$J$26, "completed", crypto_transactions!$L$2:$L$26, ">="&$P17, crypto_transactions!$L$2:$L$26, "<"&EDATE($P17, 1)) -> 1800 | S17: =Q17-R17 -> -800
B18: USDT | C18: 加密货币 (Crypto) | D18: =SUMIFS(crypto_transactions!$F$2:$F$26, crypto_transactions!$D$2:$D$26, "USDT", crypto_transactions!$C$2:$C$26, "deposit", crypto_transactions!$J$2:$J$26, "completed") -> 8000 | E18: =SUMIFS(crypto_transactions!$F$2:$F$26, crypto_transactions!$D$2:$D$26, "USDT", crypto_transactions!$C$2:$C$26, "withdrawal", crypto_transactions!$J$2:$J$26, "completed") -> 5000 | F18: =D18-E18 -> 3000 | G18: =IF(F18>0,"🟢 净流入",IF(F18=0,"⚪ 持平","🔴 净流出")) -> 🟢 净流入 | I18: ETHEREUM | J18: 以太坊 ERC-20 | K18: =COUNTIF(crypto_transactions!E2:E26, "ETHEREUM") -> 4 | L18: =COUNTIFS(crypto_transactions!E2:E26, "ETHEREUM", crypto_transactions!J2:J26, "completed") / K18 -> 1 | M18: =1 - L18 -> 0 | N18: =SUMIFS(crypto_transactions!G2:G26, crypto_transactions!E2:E26, "ETHEREUM", crypto_transactions!D2:D26, "USDT") -> 5
B19: BTC | C19: 加密货币 (Crypto) | D19: =SUMIFS(crypto_transactions!$F$2:$F$26, crypto_transactions!$D$2:$D$26, "BTC", crypto_transactions!$C$2:$C$26, "deposit", crypto_transactions!$J$2:$J$26, "completed") -> 0.081 | E19: =SUMIFS(crypto_transactions!$F$2:$F$26, crypto_transactions!$D$2:$D$26, "BTC", crypto_transactions!$C$2:$C$26, "withdrawal", crypto_transactions!$J$2:$J$26, "completed") -> 0.02 | F19: =D19-E19 -> 0.061 | G19: =IF(F19>0,"🟢 净流入",IF(F19=0,"⚪ 持平","🔴 净流出")) -> 🟢 净流入 | I19: BSC | J19: 币安智能链 BEP-20 | K19: =COUNTIF(crypto_transactions!E2:E26, "BSC") -> 4 | L19: =COUNTIFS(crypto_transactions!E2:E26, "BSC", crypto_transactions!J2:J26, "completed") / K19 -> 0.5 | M19: =1 - L19 -> 0.5 | N19: =SUMIF(crypto_transactions!E2:E26, "BSC", crypto_transactions!G2:G26) -> 1.6 | P19: 看板数据层 · 主流公链 USDT 资金流向分布 (Network USDT Distribution)
B21: ETH | C21: 加密货币 (Crypto) | D21: =SUMIFS(crypto_transactions!$F$2:$F$26, crypto_transactions!$D$2:$D$26, "ETH", crypto_transactions!$C$2:$C$26, "deposit", crypto_transactions!$J$2:$J$26, "completed") -> 0.6 | E21: =SUMIFS(crypto_transactions!$F$2:$F$26, crypto_transactions!$D$2:$D$26, "ETH", crypto_transactions!$C$2:$C$26, "withdrawal", crypto_transactions!$J$2:$J$26, "completed") -> 0.1 | F21: =D21-E21 -> 0.5 | G21: =IF(F21>0,"🟢 净流入",IF(F21=0,"⚪ 持平","🔴 净流出")) -> 🟢 净流入 | I21: ARBITRUM | J21: 以太坊 Layer-2 | K21: =COUNTIF(crypto_transactions!E2:E26, "ARBITRUM") -> 2 | L21: =COUNTIFS(crypto_transactions!E2:E26, "ARBITRUM", crypto_transactions!J2:J26, "completed") / K21 -> 0.5 | M21: =1 - L21 -> 0.5 | N21: =SUMIF(crypto_transactions!E2:E26, "ARBITRUM", crypto_transactions!G2:G26) -> 0.3 | P21: 公链网络 (Network) | Q21: 充值入金 (Deposit) | R21: 提现出金 (Withdrawal) | S21: 净沉淀量 (Net Flow)
P22: TRON | Q22: =SUMIFS(crypto_transactions!$F$2:$F$26, crypto_transactions!$E$2:$E$26, "TRON", crypto_transactions!$D$2:$D$26, "USDT", crypto_transactions!$C$2:$C$26, "deposit", crypto_transactions!$J$2:$J$26, "completed") -> 7000 | R22: =SUMIFS(crypto_transactions!$F$2:$F$26, crypto_transactions!$E$2:$E$26, "TRON", crypto_transactions!$D$2:$D$26, "USDT", crypto_transactions!$C$2:$C$26, "withdrawal", crypto_transactions!$J$2:$J$26, "completed") -> 3200 | S22: =Q22-R22 -> 3800
B23: 📈 月度资金出入与净沉淀趋势 (Monthly Flow & Net Retention Dynamics) | I23: 🌐 主流公链 USDT 流入与流出对比 (USDT Network Distribution & Net Flow) | P23: ETHEREUM | Q23: =SUMIFS(crypto_transactions!$F$2:$F$26, crypto_transactions!$E$2:$E$26, "ETHEREUM", crypto_transactions!$D$2:$D$26, "USDT", crypto_transactions!$C$2:$C$26, "deposit", crypto_transactions!$J$2:$J$26, "completed") -> 0 | R23: =SUMIFS(crypto_transactions!$F$2:$F$26, crypto_transactions!$E$2:$E$26, "ETHEREUM", crypto_transactions!$D$2:$D$26, "USDT", crypto_transactions!$C$2:$C$26, "withdrawal", crypto_transactions!$J$2:$J$26, "completed") -> 1500 | S23: =Q23-R23 -> -1500
P24: BSC | Q24: =SUMIFS(crypto_transactions!$F$2:$F$26, crypto_transactions!$E$2:$E$26, "BSC", crypto_transactions!$D$2:$D$26, "USDT", crypto_transactions!$C$2:$C$26, "deposit", crypto_transactions!$J$2:$J$26, "completed") -> 600 | R24: =SUMIFS(crypto_transactions!$F$2:$F$26, crypto_transactions!$E$2:$E$26, "BSC", crypto_transactions!$D$2:$D$26, "USDT", crypto_transactions!$C$2:$C$26, "withdrawal", crypto_transactions!$J$2:$J$26, "completed") -> 300 | S24: =Q24-R24 -> 300
P25: ARBITRUM | Q25: =SUMIFS(crypto_transactions!$F$2:$F$26, crypto_transactions!$E$2:$E$26, "ARBITRUM", crypto_transactions!$D$2:$D$26, "USDT", crypto_transactions!$C$2:$C$26, "deposit", crypto_transactions!$J$2:$J$26, "completed") -> 400 | R25: =SUMIFS(crypto_transactions!$F$2:$F$26, crypto_transactions!$E$2:$E$26, "ARBITRUM", crypto_transactions!$D$2:$D$26, "USDT", crypto_transactions!$C$2:$C$26, "withdrawal", crypto_transactions!$J$2:$J$26, "completed") -> 0 | S25: =Q25-R25 -> 400
P27: 看板数据层 · 用户资金多币种统一折算 (User Unified Flow in USDT)
P28: UID | Q28: 用户姓名 (User) | R28: 国家 (Country) | S28: KYC 等级 | T28: 充值入金折算 (USDT) | U28: 提现出金折算 (USDT) | V28: 净流动额 (USDT) | W28: 账户状态 (Status)
P29: =users!A2 -> 784231905 | Q29: =users!B2 -> Alice Chen | R29: =users!C2 -> DE | S29: =users!E2 -> 2 | T29: =(SUMIFS(fiat_transactions!$E$2:$E$26, fiat_transactions!$B$2:$B$26, P29, fiat_transactions!$C$2:$C$26, "deposit", fiat_transactions!$H$2:$H$26, "completed") * VLOOKUP(users!D2, exchange_rates!$A$2:$E$9, 5, FALSE)) + (SUMIFS(crypto_transactions!$F$2:$F$26, crypto_transactions!$B$2:$B$26, P29, crypto_transactions!$C$2:$C$26, "deposit", crypto_transactions!$J$2:$J$26, "completed", crypto_transactions!$D$2:$D$26, "USDT") * VLOOKUP("USDT", exchange_rates!$A$2:$E$9, 5, FALSE)) + (SUMIFS(crypto_transactions!$F$2:$F$26, crypto_transactions!$B$2:$B$26, P29, crypto_transactions!$C$2:$C$26, "deposit", crypto_transactions!$J$2:$J$26, "completed", crypto_transactions!$D$2:$D$26, "BTC") * VLOOKUP("BTC", exchange_rates!$A$2:$E$9, 5, FALSE)) + (SUMIFS(crypto_transactions!$F$2:$F$26, crypto_transactions!$B$2:$B$26, P29, crypto_transactions!$C$2:$C$26, "deposit", crypto_transactions!$J$2:$J$26, "completed", crypto_transactions!$D$2:$D$26, "ETH") * VLOOKUP("ETH", exchange_rates!$A$2:$E$9, 5, FALSE)) -> 5827.5 | U29: =(SUMIFS(fiat_transactions!$E$2:$E$26, fiat_transactions!$B$2:$B$26, P29, fiat_transactions!$C$2:$C$26, "withdrawal", fiat_transactions!$H$2:$H$26, "completed") * VLOOKUP(users!D2, exchange_rates!$A$2:$E$9, 5, FALSE)) + (SUMIFS(crypto_transactions!$F$2:$F$26, crypto_transactions!$B$2:$B$26, P29, crypto_transactions!$C$2:$C$26, "withdrawal", crypto_transactions!$J$2:$J$26, "completed", crypto_transactions!$D$2:$D$26, "USDT") * VLOOKUP("USDT", exchange_rates!$A$2:$E$9, 5, FALSE)) + (SUMIFS(crypto_transactions!$F$2:$F$26, crypto_transactions!$B$2:$B$26, P29, crypto_transactions!$C$2:$C$26, "withdrawal", crypto_transactions!$J$2:$J$26, "completed", crypto_transactions!$D$2:$D$26, "BTC") * VLOOKUP("BTC", exchange_rates!$A$2:$E$9, 5, FALSE)) + (SUMIFS(crypto_transactions!$F$2:$F$26, crypto_transactions!$B$2:$B$26, P29, crypto_transactions!$C$2:$C$26, "withdrawal", crypto_transactions!$J$2:$J$26, "completed", crypto_transactions!$D$2:$D$26, "ETH") * VLOOKUP("ETH", exchange_rates!$A$2:$E$9, 5, FALSE)) -> 1042.5 | V29: =T29-U29 -> 4785 | W29: =users!F2 -> active
P30: =users!A3 -> 615902374 | Q30: =users!B3 -> Bob Miller | R30: =users!C3 -> US | S30: =users!E3 -> 3 | T30: =(SUMIFS(fiat_transactions!$E$2:$E$26, fiat_transactions!$B$2:$B$26, P30, fiat_transactions!$C$2:$C$26, "deposit", fiat_transactions!$H$2:$H$26, "completed") * VLOOKUP(users!D3, exchange_rates!$A$2:$E$9, 5, FALSE)) + (SUMIFS(crypto_transactions!$F$2:$F$26, crypto_transactions!$B$2:$B$26, P30, crypto_transactions!$C$2:$C$26, "deposit", crypto_transactions!$J$2:$J$26, "completed", crypto_transactions!$D$2:$D$26, "USDT") * VLOOKUP("USDT", exchange_rates!$A$2:$E$9, 5, FALSE)) + (SUMIFS(crypto_transactions!$F$2:$F$26, crypto_transactions!$B$2:$B$26, P30, crypto_transactions!$C$2:$C$26, "deposit", crypto_transactions!$J$2:$J$26, "completed", crypto_transactions!$D$2:$D$26, "BTC") * VLOOKUP("BTC", exchange_rates!$A$2:$E$9, 5, FALSE)) + (SUMIFS(crypto_transactions!$F$2:$F$26, crypto_transactions!$B$2:$B$26, P30, crypto_transactions!$C$2:$C$26, "deposit", crypto_transactions!$J$2:$J$26, "completed", crypto_transactions!$D$2:$D$26, "ETH") * VLOOKUP("ETH", exchange_rates!$A$2:$E$9, 5, FALSE)) -> 53825 | U30: =(SUMIFS(fiat_transactions!$E$2:$E$26, fiat_transactions!$B$2:$B$26, P30, fiat_transactions!$C$2:$C$26, "withdrawal", fiat_transactions!$H$2:$H$26, "completed") * VLOOKUP(users!D3, exchange_rates!$A$2:$E$9, 5, FALSE)) + (SUMIFS(crypto_transactions!$F$2:$F$26, crypto_transactions!$B$2:$B$26, P30, crypto_transactions!$C$2:$C$26, "withdrawal", crypto_transactions!$J$2:$J$26, "completed", crypto_transactions!$D$2:$D$26, "USDT") * VLOOKUP("USDT", exchange_rates!$A$2:$E$9, 5, FALSE)) + (SUMIFS(crypto_transactions!$F$2:$F$26, crypto_transactions!$B$2:$B$26, P30, crypto_transactions!$C$2:$C$26, "withdrawal", crypto_transactions!$J$2:$J$26, "completed", crypto_transactions!$D$2:$D$26, "BTC") * VLOOKUP("BTC", exchange_rates!$A$2:$E$9, 5, FALSE)) + (SUMIFS(crypto_transactions!$F$2:$F$26, crypto_transactions!$B$2:$B$26, P30, crypto_transactions!$C$2:$C$26, "withdrawal", crypto_transactions!$J$2:$J$26, "completed", crypto_transactions!$D$2:$D$26, "ETH") * VLOOKUP("ETH", exchange_rates!$A$2:$E$9, 5, FALSE)) -> 18290 | V30: =T30-U30 -> 35535 | W30: =users!F3 -> active
P31: =users!A4 -> 903174628 | Q31: =users!B4 -> Charlie Tanaka | R31: =users!C4 -> JP | S31: =users!E4 -> 1 | T31: =(SUMIFS(fiat_transactions!$E$2:$E$26, fiat_transactions!$B$2:$B$26, P31, fiat_transactions!$C$2:$C$26, "deposit", fiat_transactions!$H$2:$H$26, "completed") * VLOOKUP(users!D4, exchange_rates!$A$2:$E$9, 5, FALSE)) + (SUMIFS(crypto_transactions!$F$2:$F$26, crypto_transactions!$B$2:$B$26, P31, crypto_transactions!$C$2:$C$26, "deposit", crypto_transactions!$J$2:$J$26, "completed", crypto_transactions!$D$2:$D$26, "USDT") * VLOOKUP("USDT", exchange_rates!$A$2:$E$9, 5, FALSE)) + (SUMIFS(crypto_transactions!$F$2:$F$26, crypto_transactions!$B$2:$B$26, P31, crypto_transactions!$C$2:$C$26, "deposit", crypto_transactions!$J$2:$J$26, "completed", crypto_transactions!$D$2:$D$26, "BTC") * VLOOKUP("BTC", exchange_rates!$A$2:$E$9, 5, FALSE)) + (SUMIFS(crypto_transactions!$F$2:$F$26, crypto_transactions!$B$2:$B$26, P31, crypto_transactions!$C$2:$C$26, "deposit", crypto_transactions!$J$2:$J$26, "completed", crypto_transactions!$D$2:$D$26, "ETH") * VLOOKUP("ETH", exchange_rates!$A$2:$E$9, 5, FALSE)) -> 1400 | U31: =(SUMIFS(fiat_transactions!$E$2:$E$26, fiat_transactions!$B$2:$B$26, P31, fiat_transactions!$C$2:$C$26, "withdrawal", fiat_transactions!$H$2:$H$26, "completed") * VLOOKUP(users!D4, exchange_rates!$A$2:$E$9, 5, FALSE)) + (SUMIFS(crypto_transactions!$F$2:$F$26, crypto_transactions!$B$2:$B$26, P31, crypto_transactions!$C$2:$C$26, "withdrawal", crypto_transactions!$J$2:$J$26, "completed", crypto_transactions!$D$2:$D$26, "USDT") * VLOOKUP("USDT", exchange_rates!$A$2:$E$9, 5, FALSE)) + (SUMIFS(crypto_transactions!$F$2:$F$26, crypto_transactions!$B$2:$B$26, P31, crypto_transactions!$C$2:$C$26, "withdrawal", crypto_transactions!$J$2:$J$26, "completed", crypto_transactions!$D$2:$D$26, "BTC") * VLOOKUP("BTC", exchange_rates!$A$2:$E$9, 5, FALSE)) + (SUMIFS(crypto_transactions!$F$2:$F$26, crypto_transactions!$B$2:$B$26, P31, crypto_transactions!$C$2:$C$26, "withdrawal", crypto_transactions!$J$2:$J$26, "completed", crypto_transactions!$D$2:$D$26, "ETH") * VLOOKUP("ETH", exchange_rates!$A$2:$E$9, 5, FALSE)) -> 750 | V31: =T31-U31 -> 650 | W31: =users!F4 -> active
P32: =users!A5 -> 528406193 | Q32: =users!B5 -> David Smith | R32: =users!C5 -> GB | S32: =users!E5 -> 2 | T32: =(SUMIFS(fiat_transactions!$E$2:$E$26, fiat_transactions!$B$2:$B$26, P32, fiat_transactions!$C$2:$C$26, "deposit", fiat_transactions!$H$2:$H$26, "completed") * VLOOKUP(users!D5, exchange_rates!$A$2:$E$9, 5, FALSE)) + (SUMIFS(crypto_transactions!$F$2:$F$26, crypto_transactions!$B$2:$B$26, P32, crypto_transactions!$C$2:$C$26, "deposit", crypto_transactions!$J$2:$J$26, "completed", crypto_transactions!$D$2:$D$26, "USDT") * VLOOKUP("USDT", exchange_rates!$A$2:$E$9, 5, FALSE)) + (SUMIFS(crypto_transactions!$F$2:$F$26, crypto_transactions!$B$2:$B$26, P32, crypto_transactions!$C$2:$C$26, "deposit", crypto_transactions!$J$2:$J$26, "completed", crypto_transactions!$D$2:$D$26, "BTC") * VLOOKUP("BTC", exchange_rates!$A$2:$E$9, 5, FALSE)) + (SUMIFS(crypto_transactions!$F$2:$F$26, crypto_transactions!$B$2:$B$26, P32, crypto_transactions!$C$2:$C$26, "deposit", crypto_transactions!$J$2:$J$26, "completed", crypto_transactions!$D$2:$D$26, "ETH") * VLOOKUP("ETH", exchange_rates!$A$2:$E$9, 5, FALSE)) -> 4555 | U32: =(SUMIFS(fiat_transactions!$E$2:$E$26, fiat_transactions!$B$2:$B$26, P32, fiat_transactions!$C$2:$C$26, "withdrawal", fiat_transactions!$H$2:$H$26, "completed") * VLOOKUP(users!D5, exchange_rates!$A$2:$E$9, 5, FALSE)) + (SUMIFS(crypto_transactions!$F$2:$F$26, crypto_transactions!$B$2:$B$26, P32, crypto_transactions!$C$2:$C$26, "withdrawal", crypto_transactions!$J$2:$J$26, "completed", crypto_transactions!$D$2:$D$26, "USDT") * VLOOKUP("USDT", exchange_rates!$A$2:$E$9, 5, FALSE)) + (SUMIFS(crypto_transactions!$F$2:$F$26, crypto_transactions!$B$2:$B$26, P32, crypto_transactions!$C$2:$C$26, "withdrawal", crypto_transactions!$J$2:$J$26, "completed", crypto_transactions!$D$2:$D$26, "BTC") * VLOOKUP("BTC", exchange_rates!$A$2:$E$9, 5, FALSE)) + (SUMIFS(crypto_transactions!$F$2:$F$26, crypto_transactions!$B$2:$B$26, P32, crypto_transactions!$C$2:$C$26, "withdrawal", crypto_transactions!$J$2:$J$26, "completed", crypto_transactions!$D$2:$D$26, "ETH") * VLOOKUP("ETH", exchange_rates!$A$2:$E$9, 5, FALSE)) -> 4370 | V32: =T32-U32 -> 185 | W32: =users!F5 -> active
P33: =users!A6 -> 846219537 | Q33: =users!B6 -> Elena Rostova | R33: =users!C6 -> FR | S33: =users!E6 -> 2 | T33: =(SUMIFS(fiat_transactions!$E$2:$E$26, fiat_transactions!$B$2:$B$26, P33, fiat_transactions!$C$2:$C$26, "deposit", fiat_transactions!$H$2:$H$26, "completed") * VLOOKUP(users!D6, exchange_rates!$A$2:$E$9, 5, FALSE)) + (SUMIFS(crypto_transactions!$F$2:$F$26, crypto_transactions!$B$2:$B$26, P33, crypto_transactions!$C$2:$C$26, "deposit", crypto_transactions!$J$2:$J$26, "completed", crypto_transactions!$D$2:$D$26, "USDT") * VLOOKUP("USDT", exchange_rates!$A$2:$E$9, 5, FALSE)) + (SUMIFS(crypto_transactions!$F$2:$F$26, crypto_transactions!$B$2:$B$26, P33, crypto_transactions!$C$2:$C$26, "deposit", crypto_transactions!$J$2:$J$26, "completed", crypto_transactions!$D$2:$D$26, "BTC") * VLOOKUP("BTC", exchange_rates!$A$2:$E$9, 5, FALSE)) + (SUMIFS(crypto_transactions!$F$2:$F$26, crypto_transactions!$B$2:$B$26, P33, crypto_transactions!$C$2:$C$26, "deposit", crypto_transactions!$J$2:$J$26, "completed", crypto_transactions!$D$2:$D$26, "ETH") * VLOOKUP("ETH", exchange_rates!$A$2:$E$9, 5, FALSE)) -> 8570 | U33: =(SUMIFS(fiat_transactions!$E$2:$E$26, fiat_transactions!$B$2:$B$26, P33, fiat_transactions!$C$2:$C$26, "withdrawal", fiat_transactions!$H$2:$H$26, "completed") * VLOOKUP(users!D6, exchange_rates!$A$2:$E$9, 5, FALSE)) + (SUMIFS(crypto_transactions!$F$2:$F$26, crypto_transactions!$B$2:$B$26, P33, crypto_transactions!$C$2:$C$26, "withdrawal", crypto_transactions!$J$2:$J$26, "completed", crypto_transactions!$D$2:$D$26, "USDT") * VLOOKUP("USDT", exchange_rates!$A$2:$E$9, 5, FALSE)) + (SUMIFS(crypto_transactions!$F$2:$F$26, crypto_transactions!$B$2:$B$26, P33, crypto_transactions!$C$2:$C$26, "withdrawal", crypto_transactions!$J$2:$J$26, "completed", crypto_transactions!$D$2:$D$26, "BTC") * VLOOKUP("BTC", exchange_rates!$A$2:$E$9, 5, FALSE)) + (SUMIFS(crypto_transactions!$F$2:$F$26, crypto_transactions!$B$2:$B$26, P33, crypto_transactions!$C$2:$C$26, "withdrawal", crypto_transactions!$J$2:$J$26, "completed", crypto_transactions!$D$2:$D$26, "ETH") * VLOOKUP("ETH", exchange_rates!$A$2:$E$9, 5, FALSE)) -> 265 | V33: =T33-U33 -> 8305 | W33: =users!F6 -> active
P34: =users!A7 -> 692481305 | Q34: =users!B7 -> Fatimah Al-Sayed | R34: =users!C7 -> AE | S34: =users!E7 -> 3 | T34: =(SUMIFS(fiat_transactions!$E$2:$E$26, fiat_transactions!$B$2:$B$26, P34, fiat_transactions!$C$2:$C$26, "deposit", fiat_transactions!$H$2:$H$26, "completed") * VLOOKUP(users!D7, exchange_rates!$A$2:$E$9, 5, FALSE)) + (SUMIFS(crypto_transactions!$F$2:$F$26, crypto_transactions!$B$2:$B$26, P34, crypto_transactions!$C$2:$C$26, "deposit", crypto_transactions!$J$2:$J$26, "completed", crypto_transactions!$D$2:$D$26, "USDT") * VLOOKUP("USDT", exchange_rates!$A$2:$E$9, 5, FALSE)) + (SUMIFS(crypto_transactions!$F$2:$F$26, crypto_transactions!$B$2:$B$26, P34, crypto_transactions!$C$2:$C$26, "deposit", crypto_transactions!$J$2:$J$26, "completed", crypto_transactions!$D$2:$D$26, "BTC") * VLOOKUP("BTC", exchange_rates!$A$2:$E$9, 5, FALSE)) + (SUMIFS(crypto_transactions!$F$2:$F$26, crypto_transactions!$B$2:$B$26, P34, crypto_transactions!$C$2:$C$26, "deposit", crypto_transactions!$J$2:$J$26, "completed", crypto_transactions!$D$2:$D$26, "ETH") * VLOOKUP("ETH", exchange_rates!$A$2:$E$9, 5, FALSE)) -> 28935 | U34: =(SUMIFS(fiat_transactions!$E$2:$E$26, fiat_transactions!$B$2:$B$26, P34, fiat_transactions!$C$2:$C$26, "withdrawal", fiat_transactions!$H$2:$H$26, "completed") * VLOOKUP(users!D7, exchange_rates!$A$2:$E$9, 5, FALSE)) + (SUMIFS(crypto_transactions!$F$2:$F$26, crypto_transactions!$B$2:$B$26, P34, crypto_transactions!$C$2:$C$26, "withdrawal", crypto_transactions!$J$2:$J$26, "completed", crypto_transactions!$D$2:$D$26, "USDT") * VLOOKUP("USDT", exchange_rates!$A$2:$E$9, 5, FALSE)) + (SUMIFS(crypto_transactions!$F$2:$F$26, crypto_transactions!$B$2:$B$26, P34, crypto_transactions!$C$2:$C$26, "withdrawal", crypto_transactions!$J$2:$J$26, "completed", crypto_transactions!$D$2:$D$26, "BTC") * VLOOKUP("BTC", exchange_rates!$A$2:$E$9, 5, FALSE)) + (SUMIFS(crypto_transactions!$F$2:$F$26, crypto_transactions!$B$2:$B$26, P34, crypto_transactions!$C$2:$C$26, "withdrawal", crypto_transactions!$J$2:$J$26, "completed", crypto_transactions!$D$2:$D$26, "ETH") * VLOOKUP("ETH", exchange_rates!$A$2:$E$9, 5, FALSE)) -> 10600 | V34: =T34-U34 -> 18335 | W34: =users!F7 -> active
P35: =users!A8 -> 438750921 | Q35: =users!B8 -> Gabriel Garcia | R35: =users!C8 -> BR | S35: =users!E8 -> 2 | T35: =(SUMIFS(fiat_transactions!$E$2:$E$26, fiat_transactions!$B$2:$B$26, P35, fiat_transactions!$C$2:$C$26, "deposit", fiat_transactions!$H$2:$H$26, "completed") * VLOOKUP(users!D8, exchange_rates!$A$2:$E$9, 5, FALSE)) + (SUMIFS(crypto_transactions!$F$2:$F$26, crypto_transactions!$B$2:$B$26, P35, crypto_transactions!$C$2:$C$26, "deposit", crypto_transactions!$J$2:$J$26, "completed", crypto_transactions!$D$2:$D$26, "USDT") * VLOOKUP("USDT", exchange_rates!$A$2:$E$9, 5, FALSE)) + (SUMIFS(crypto_transactions!$F$2:$F$26, crypto_transactions!$B$2:$B$26, P35, crypto_transactions!$C$2:$C$26, "deposit", crypto_transactions!$J$2:$J$26, "completed", crypto_transactions!$D$2:$D$26, "BTC") * VLOOKUP("BTC", exchange_rates!$A$2:$E$9, 5, FALSE)) + (SUMIFS(crypto_transactions!$F$2:$F$26, crypto_transactions!$B$2:$B$26, P35, crypto_transactions!$C$2:$C$26, "deposit", crypto_transactions!$J$2:$J$26, "completed", crypto_transactions!$D$2:$D$26, "ETH") * VLOOKUP("ETH", exchange_rates!$A$2:$E$9, 5, FALSE)) -> 2255 | U35: =(SUMIFS(fiat_transactions!$E$2:$E$26, fiat_transactions!$B$2:$B$26, P35, fiat_transactions!$C$2:$C$26, "withdrawal", fiat_transactions!$H$2:$H$26, "completed") * VLOOKUP(users!D8, exchange_rates!$A$2:$E$9, 5, FALSE)) + (SUMIFS(crypto_transactions!$F$2:$F$26, crypto_transactions!$B$2:$B$26, P35, crypto_transactions!$C$2:$C$26, "withdrawal", crypto_transactions!$J$2:$J$26, "completed", crypto_transactions!$D$2:$D$26, "USDT") * VLOOKUP("USDT", exchange_rates!$A$2:$E$9, 5, FALSE)) + (SUMIFS(crypto_transactions!$F$2:$F$26, crypto_transactions!$B$2:$B$26, P35, crypto_transactions!$C$2:$C$26, "withdrawal", crypto_transactions!$J$2:$J$26, "completed", crypto_transactions!$D$2:$D$26, "BTC") * VLOOKUP("BTC", exchange_rates!$A$2:$E$9, 5, FALSE)) + (SUMIFS(crypto_transactions!$F$2:$F$26, crypto_transactions!$B$2:$B$26, P35, crypto_transactions!$C$2:$C$26, "withdrawal", crypto_transactions!$J$2:$J$26, "completed", crypto_transactions!$D$2:$D$26, "ETH") * VLOOKUP("ETH", exchange_rates!$A$2:$E$9, 5, FALSE)) -> 2255 | V35: =T35-U35 -> 0 | W35: =users!F8 -> active
P36: =users!A9 -> 319582046 | Q36: =users!B9 -> Hakan Yilmaz | R36: =users!C9 -> TR | S36: =users!E9 -> 1 | T36: =(SUMIFS(fiat_transactions!$E$2:$E$26, fiat_transactions!$B$2:$B$26, P36, fiat_transactions!$C$2:$C$26, "deposit", fiat_transactions!$H$2:$H$26, "completed") * VLOOKUP(users!D9, exchange_rates!$A$2:$E$9, 5, FALSE)) + (SUMIFS(crypto_transactions!$F$2:$F$26, crypto_transactions!$B$2:$B$26, P36, crypto_transactions!$C$2:$C$26, "deposit", crypto_transactions!$J$2:$J$26, "completed", crypto_transactions!$D$2:$D$26, "USDT") * VLOOKUP("USDT", exchange_rates!$A$2:$E$9, 5, FALSE)) + (SUMIFS(crypto_transactions!$F$2:$F$26, crypto_transactions!$B$2:$B$26, P36, crypto_transactions!$C$2:$C$26, "deposit", crypto_transactions!$J$2:$J$26, "completed", crypto_transactions!$D$2:$D$26, "BTC") * VLOOKUP("BTC", exchange_rates!$A$2:$E$9, 5, FALSE)) + (SUMIFS(crypto_transactions!$F$2:$F$26, crypto_transactions!$B$2:$B$26, P36, crypto_transactions!$C$2:$C$26, "deposit", crypto_transactions!$J$2:$J$26, "completed", crypto_transactions!$D$2:$D$26, "ETH") * VLOOKUP("ETH", exchange_rates!$A$2:$E$9, 5, FALSE)) -> 507 | U36: =(SUMIFS(fiat_transactions!$E$2:$E$26, fiat_transactions!$B$2:$B$26, P36, fiat_transactions!$C$2:$C$26, "withdrawal", fiat_transactions!$H$2:$H$26, "completed") * VLOOKUP(users!D9, exchange_rates!$A$2:$E$9, 5, FALSE)) + (SUMIFS(crypto_transactions!$F$2:$F$26, crypto_transactions!$B$2:$B$26, P36, crypto_transactions!$C$2:$C$26, "withdrawal", crypto_transactions!$J$2:$J$26, "completed", crypto_transactions!$D$2:$D$26, "USDT") * VLOOKUP("USDT", exchange_rates!$A$2:$E$9, 5, FALSE)) + (SUMIFS(crypto_transactions!$F$2:$F$26, crypto_transactions!$B$2:$B$26, P36, crypto_transactions!$C$2:$C$26, "withdrawal", crypto_transactions!$J$2:$J$26, "completed", crypto_transactions!$D$2:$D$26, "BTC") * VLOOKUP("BTC", exchange_rates!$A$2:$E$9, 5, FALSE)) + (SUMIFS(crypto_transactions!$F$2:$F$26, crypto_transactions!$B$2:$B$26, P36, crypto_transactions!$C$2:$C$26, "withdrawal", crypto_transactions!$J$2:$J$26, "completed", crypto_transactions!$D$2:$D$26, "ETH") * VLOOKUP("ETH", exchange_rates!$A$2:$E$9, 5, FALSE)) -> 177 | V36: =T36-U36 -> 330 | W36: =users!F9 -> active
B37: 🚨 核心合规与账户风控处置矩阵 (Compliance & AML Incident Matrix) | I37: ⚠️ 链上阻塞与清算挂起处置矩阵 (On-Chain & Clearing Exceptions Matrix) | P37: =users!A10 -> 502847193 | Q37: =users!B10 -> Irene Jung | R37: =users!C10 -> KR | S37: =users!E10 -> 2 | T37: =(SUMIFS(fiat_transactions!$E$2:$E$26, fiat_transactions!$B$2:$B$26, P37, fiat_transactions!$C$2:$C$26, "deposit", fiat_transactions!$H$2:$H$26, "completed") * VLOOKUP(users!D10, exchange_rates!$A$2:$E$9, 5, FALSE)) + (SUMIFS(crypto_transactions!$F$2:$F$26, crypto_transactions!$B$2:$B$26, P37, crypto_transactions!$C$2:$C$26, "deposit", crypto_transactions!$J$2:$J$26, "completed", crypto_transactions!$D$2:$D$26, "USDT") * VLOOKUP("USDT", exchange_rates!$A$2:$E$9, 5, FALSE)) + (SUMIFS(crypto_transactions!$F$2:$F$26, crypto_transactions!$B$2:$B$26, P37, crypto_transactions!$C$2:$C$26, "deposit", crypto_transactions!$J$2:$J$26, "completed", crypto_transactions!$D$2:$D$26, "BTC") * VLOOKUP("BTC", exchange_rates!$A$2:$E$9, 5, FALSE)) + (SUMIFS(crypto_transactions!$F$2:$F$26, crypto_transactions!$B$2:$B$26, P37, crypto_transactions!$C$2:$C$26, "deposit", crypto_transactions!$J$2:$J$26, "completed", crypto_transactions!$D$2:$D$26, "ETH") * VLOOKUP("ETH", exchange_rates!$A$2:$E$9, 5, FALSE)) -> 0 | U37: =(SUMIFS(fiat_transactions!$E$2:$E$26, fiat_transactions!$B$2:$B$26, P37, fiat_transactions!$C$2:$C$26, "withdrawal", fiat_transactions!$H$2:$H$26, "completed") * VLOOKUP(users!D10, exchange_rates!$A$2:$E$9, 5, FALSE)) + (SUMIFS(crypto_transactions!$F$2:$F$26, crypto_transactions!$B$2:$B$26, P37, crypto_transactions!$C$2:$C$26, "withdrawal", crypto_transactions!$J$2:$J$26, "completed", crypto_transactions!$D$2:$D$26, "USDT") * VLOOKUP("USDT", exchange_rates!$A$2:$E$9, 5, FALSE)) + (SUMIFS(crypto_transactions!$F$2:$F$26, crypto_transactions!$B$2:$B$26, P37, crypto_transactions!$C$2:$C$26, "withdrawal", crypto_transactions!$J$2:$J$26, "completed", crypto_transactions!$D$2:$D$26, "BTC") * VLOOKUP("BTC", exchange_rates!$A$2:$E$9, 5, FALSE)) + (SUMIFS(crypto_transactions!$F$2:$F$26, crypto_transactions!$B$2:$B$26, P37, crypto_transactions!$C$2:$C$26, "withdrawal", crypto_transactions!$J$2:$J$26, "completed", crypto_transactions!$D$2:$D$26, "ETH") * VLOOKUP("ETH", exchange_rates!$A$2:$E$9, 5, FALSE)) -> 820 | V37: =T37-U37 -> -820 | W37: =users!F10 -> frozen
B38: 风险等级 | C38: 涉案用户 | D38: 关联订单号 | E38: 涉及金额 | F38: 违规成因 / 诊断 | G38: 运营处置与跟进动作 | I38: 异常类型 | J38: 涉及网络/通道 | K38: 关联订单号 | L38: 涉及金额 | M38: 技术根因 / 诊断 | N38: 处置建议与恢复动作 | P38: =users!A11 -> 219485730 | Q38: =users!B11 -> Jonas Weber | R38: =users!C11 -> DE | S38: =users!E11 -> 0 | T38: =(SUMIFS(fiat_transactions!$E$2:$E$26, fiat_transactions!$B$2:$B$26, P38, fiat_transactions!$C$2:$C$26, "deposit", fiat_transactions!$H$2:$H$26, "completed") * VLOOKUP(users!D11, exchange_rates!$A$2:$E$9, 5, FALSE)) + (SUMIFS(crypto_transactions!$F$2:$F$26, crypto_transactions!$B$2:$B$26, P38, crypto_transactions!$C$2:$C$26, "deposit", crypto_transactions!$J$2:$J$26, "completed", crypto_transactions!$D$2:$D$26, "USDT") * VLOOKUP("USDT", exchange_rates!$A$2:$E$9, 5, FALSE)) + (SUMIFS(crypto_transactions!$F$2:$F$26, crypto_transactions!$B$2:$B$26, P38, crypto_transactions!$C$2:$C$26, "deposit", crypto_transactions!$J$2:$J$26, "completed", crypto_transactions!$D$2:$D$26, "BTC") * VLOOKUP("BTC", exchange_rates!$A$2:$E$9, 5, FALSE)) + (SUMIFS(crypto_transactions!$F$2:$F$26, crypto_transactions!$B$2:$B$26, P38, crypto_transactions!$C$2:$C$26, "deposit", crypto_transactions!$J$2:$J$26, "completed", crypto_transactions!$D$2:$D$26, "ETH") * VLOOKUP("ETH", exchange_rates!$A$2:$E$9, 5, FALSE)) -> 0 | U38: =(SUMIFS(fiat_transactions!$E$2:$E$26, fiat_transactions!$B$2:$B$26, P38, fiat_transactions!$C$2:$C$26, "withdrawal", fiat_transactions!$H$2:$H$26, "completed") * VLOOKUP(users!D11, exchange_rates!$A$2:$E$9, 5, FALSE)) + (SUMIFS(crypto_transactions!$F$2:$F$26, crypto_transactions!$B$2:$B$26, P38, crypto_transactions!$C$2:$C$26, "withdrawal", crypto_transactions!$J$2:$J$26, "completed", crypto_transactions!$D$2:$D$26, "USDT") * VLOOKUP("USDT", exchange_rates!$A$2:$E$9, 5, FALSE)) + (SUMIFS(crypto_transactions!$F$2:$F$26, crypto_transactions!$B$2:$B$26, P38, crypto_transactions!$C$2:$C$26, "withdrawal", crypto_transactions!$J$2:$J$26, "completed", crypto_transactions!$D$2:$D$26, "BTC") * VLOOKUP("BTC", exchange_rates!$A$2:$E$9, 5, FALSE)) + (SUMIFS(crypto_transactions!$F$2:$F$26, crypto_transactions!$B$2:$B$26, P38, crypto_transactions!$C$2:$C$26, "withdrawal", crypto_transactions!$J$2:$J$26, "completed", crypto_transactions!$D$2:$D$26, "ETH") * VLOOKUP("ETH", exchange_rates!$A$2:$E$9, 5, FALSE)) -> 0 | V38: =T38-U38 -> 0 | W38: =users!F11 -> pending_kyc
B39: 🔴 严重拦截失效 | C39: Irene Jung | D39: fo_20250920_50284719 | E39: $800.00 USD | F39: 【冻结账户出金】用户处于 frozen 状态，ACH 仍放行 $800 出金 | G39: 立即冻结下游清算通道，排查网关拦截切面，追索未到账资金 | I39: 🟠 广播卡单 | J39: ARBITRUM | K39: co_20251220_90317464 | L39: 250.00 USDT | M39: 【TxHash 为空】提现 processing 且确认数 0 | N39: 核查 L2 节点 RPC 状态，执行重广播或人工退回冲正 | P39: 合计 (Total) | T39: =SUM(T29:T38) -> 105874.5 | U39: =SUM(U29:U38) -> 38569.5 | V39: =SUM(V29:V38) -> 67305 | W39: 10 户全量
B40: 🔴 严重拦截失效 | C40: Irene Jung | D40: fo_20251025_50284720 | E40: $20.00 USD | F40: 【二次渗透出金】同用户再次成功渗透出金 $20 | G40: 紧急注销该用户 API 密钥，升级前置拦截中间件与限额熔断 | I40: 🟡 确认中延迟 | J40: BSC | K40: co_20250801_69248133 | L40: 500.00 USDT | M40: 【确认数滞后】充值处于 confirming (5/15 确认) | N40: 持续监控 BSC 主网出块，达标后自动触发充值上账
B41: 🟡 准入合规排查 | C41: Jonas Weber | D41: 无在途订单 | E41: €0.00 EUR | F41: 【准入风控】KYC Level 0 挂起中 | G41: 限制账户充提与交易功能，催促用户提交实名认证材料以防死账 | I41: 🟡 大额电汇在途 | J41: wire_transfer | K41: fo_20250720_61590240 | L41: $10,000.00 USD | M41: 【Swift 结算在途】Bob Miller 大额电汇 pending | N41: 专人向结算行索取 MT103 凭证，核实推进资金入账
B42: 🟢 规则校验合规 | C42: 全局风控引擎 | D42: 17/17 QA Passed | E42: -- | F42: 【质检基线】全量交易与余额对账规则 100% 验证通过 | G42: 保持实时风控旁路监听，持续监控高频出金异动 | I42: 🔴 链上广播失败 | J42: BSC | K42: co_20251201_69248134 | L42: 300.00 USDT | M42: 【节点广播超时】提现订单 failed，TxHash 未生成 | N42: 执行资金解冻并返还用户主账户，提醒用户重新发起
B44: 👥 用户 KYC 认证等级资金分布穿透 (Capital Distribution by KYC Level) | I44: 🌍 国家与地区资金流动穿透 (Cross-Border Capital Flow by Country/Region)
B45: KYC 认证等级 | C45: 用户数 (Users) | D45: 充值入金 (USDT) | E45: 提现出金 (USDT) | F45: 净流动额 (USDT) | G45: 资金沉淀率 (Retention) | I45: 国家 / 地区 | J45: 核心币种 | K45: 充值入金 (USDT) | L45: 提现出金 (USDT) | M45: 净流动额 (USDT) | N45: 流动状态 (Flow Status)
B46: KYC Level 0 (待认证) | C46: =COUNTIF($S$29:$S$38, 0) -> 1 | D46: =SUMIF($S$29:$S$38, 0, $T$29:$T$38) -> 0 | E46: =SUMIF($S$29:$S$38, 0, $U$29:$U$38) -> 0 | F46: =D46-E46 -> 0 | G46: =IF(D46=0, 0, F46/D46) -> 0 | I46: 🇺🇸 US (美国) | J46: USD | K46: =SUMIF($R$29:$R$38, "US", $T$29:$T$38) -> 53825 | L46: =SUMIF($R$29:$R$38, "US", $U$29:$U$38) -> 18290 | M46: =K46-L46 -> 35535 | N46: =IF(M46>0, "🟢 净流入", IF(M46=0, "⚪ 持平", "🔴 净流出")) -> 🟢 净流入
B47: KYC Level 1 (初级认证) | C47: =COUNTIF($S$29:$S$38, 1) -> 2 | D47: =SUMIF($S$29:$S$38, 1, $T$29:$T$38) -> 1907 | E47: =SUMIF($S$29:$S$38, 1, $U$29:$U$38) -> 927 | F47: =D47-E47 -> 980 | G47: =IF(D47=0, 0, F47/D47) -> 0.51389617 | I47: 🇦🇪 AE (阿联酋) | J47: USD | K47: =SUMIF($R$29:$R$38, "AE", $T$29:$T$38) -> 28935 | L47: =SUMIF($R$29:$R$38, "AE", $U$29:$U$38) -> 10600 | M47: =K47-L47 -> 18335 | N47: =IF(M47>0, "🟢 净流入", IF(M47=0, "⚪ 持平", "🔴 净流出")) -> 🟢 净流入
B48: KYC Level 2 (标准认证) | C48: =COUNTIF($S$29:$S$38, 2) -> 5 | D48: =SUMIF($S$29:$S$38, 2, $T$29:$T$38) -> 21207.5 | E48: =SUMIF($S$29:$S$38, 2, $U$29:$U$38) -> 8752.5 | F48: =D48-E48 -> 12455 | G48: =IF(D48=0, 0, F48/D48) -> 0.58729223 | I48: 🇫🇷 FR (法国) | J48: EUR | K48: =SUMIF($R$29:$R$38, "FR", $T$29:$T$38) -> 8570 | L48: =SUMIF($R$29:$R$38, "FR", $U$29:$U$38) -> 265 | M48: =K48-L48 -> 8305 | N48: =IF(M48>0, "🟢 净流入", IF(M48=0, "⚪ 持平", "🔴 净流出")) -> 🟢 净流入
B49: KYC Level 3 (高级认证) | C49: =COUNTIF($S$29:$S$38, 3) -> 2 | D49: =SUMIF($S$29:$S$38, 3, $T$29:$T$38) -> 82760 | E49: =SUMIF($S$29:$S$38, 3, $U$29:$U$38) -> 28890 | F49: =D49-E49 -> 53870 | G49: =IF(D49=0, 0, F49/D49) -> 0.65091832 | I49: 🇩🇪 DE (德国) | J49: EUR | K49: =SUMIF($R$29:$R$38, "DE", $T$29:$T$38) -> 5827.5 | L49: =SUMIF($R$29:$R$38, "DE", $U$29:$U$38) -> 1042.5 | M49: =K49-L49 -> 4785 | N49: =IF(M49>0, "🟢 净流入", IF(M49=0, "⚪ 持平", "🔴 净流出")) -> 🟢 净流入
B50: 合计 (Total) | C50: =SUM(C46:C49) -> 10 | D50: =SUM(D46:D49) -> 105874.5 | E50: =SUM(E46:E49) -> 38569.5 | F50: =SUM(F46:F49) -> 67305 | G50: =IF(D50=0, 0, F50/D50) -> 0.63570548 | I50: 🇬🇧 GB (英国) | J50: GBP | K50: =SUMIF($R$29:$R$38, "GB", $T$29:$T$38) -> 4555 | L50: =SUMIF($R$29:$R$38, "GB", $U$29:$U$38) -> 4370 | M50: =K50-L50 -> 185 | N50: =IF(M50>0, "🟢 净流入", IF(M50=0, "⚪ 持平", "🔴 净流出")) -> 🟢 净流入
B51: 💡 风控洞察 | C51: Level 3 高级用户贡献 80.0% 净沉淀额 ($53.8k)，为交易所核心资金支柱 | I51: 🇧🇷 BR (巴西) | J51: BRL | K51: =SUMIF($R$29:$R$38, "BR", $T$29:$T$38) -> 2255 | L51: =SUMIF($R$29:$R$38, "BR", $U$29:$U$38) -> 2255 | M51: =K51-L51 -> 0 | N51: =IF(M51>0, "🟢 净流入", IF(M51=0, "⚪ 持平", "🔴 净流出")) -> ⚪ 持平
B52: ⚠️ 重点警示 | C52: Level 2 标准用户中包含已冻结账户 Irene Jung，发生越权渗透出金 $820 | I52: 🇯🇵 JP (日本) | J52: USD | K52: =SUMIF($R$29:$R$38, "JP", $T$29:$T$38) -> 1400 | L52: =SUMIF($R$29:$R$38, "JP", $U$29:$U$38) -> 750 | M52: =K52-L52 -> 650 | N52: =IF(M52>0, "🟢 净流入", IF(M52=0, "⚪ 持平", "🔴 净流出")) -> 🟢 净流入
B53: 🛡️ 处置建议 | C53: 针对 Level 0 (Jonas Weber) 阻断提现并催告认证；加固出金网关拦截切面 | I53: 🇹🇷 TR (土耳其) | J53: TRY | K53: =SUMIF($R$29:$R$38, "TR", $T$29:$T$38) -> 507 | L53: =SUMIF($R$29:$R$38, "TR", $U$29:$U$38) -> 177 | M53: =K53-L53 -> 330 | N53: =IF(M53>0, "🟢 净流入", IF(M53=0, "⚪ 持平", "🔴 净流出")) -> 🟢 净流入
B54: 🟢 审计基线 | C54: 全量交易与余额对账规则 100% 验证通过 (CHK_REC_01 / CHK_REC_02) | I54: 🇰🇷 KR (韩国) | J54: USD | K54: =SUMIF($R$29:$R$38, "KR", $T$29:$T$38) -> 0 | L54: =SUMIF($R$29:$R$38, "KR", $U$29:$U$38) -> 820 | M54: =K54-L54 -> -820 | N54: =IF(M54>0, "🟢 净流入", IF(M54=0, "⚪ 持平", "🔴 净流出")) -> 🔴 净流出
B55: 全域基线 | C55: 全量 10 户画像及资金对账 100% 吻合 | 核心流动性充足 | I55: 合计 (Total) | J55: 多币种 | K55: =SUM(K46:K54) -> 105874.5 | L55: =SUM(L46:L54) -> 38569.5 | M55: =SUM(M46:M54) -> 67305 | N55: 🟢 全局净流入

Sheet users
A1: uid | B1: user_name | C1: country_code | D1: base_fiat_currency | E1: kyc_level | F1: account_status | G1: created_at
A2: 784231905 | B2: Alice Chen | C2: DE | D2: EUR | E2: 2 | F2: active | G2: 45306.354
A3: 615902374 | B3: Bob Miller | C3: US | D3: USD | E3: 3 | F3: active | G3: 45332.594
A4: 903174628 | B4: Charlie Tanaka | C4: JP | D4: USD | E4: 1 | F4: active | G4: 45356.406
A5: 528406193 | B5: David Smith | C5: GB | D5: GBP | E5: 2 | F5: active | G5: 45394.472
A6: 846219537 | B6: Elena Rostova | C6: FR | D6: EUR | E6: 2 | F6: active | G6: 45430.694
A7: 692481305 | B7: Fatimah Al-Sayed | C7: AE | D7: USD | E7: 3 | F7: active | G7: 45444.424
A8: 438750921 | B8: Gabriel Garcia | C8: BR | D8: BRL | E8: 2 | F8: active | G8: 45495.542
A9: 319582046 | B9: Hakan Yilmaz | C9: TR | D9: TRY | E9: 1 | F9: active | G9: 45534.642
A10: 502847193 | B10: Irene Jung | C10: KR | D10: USD | E10: 2 | F10: frozen | G10: 45549.785
A11: 219485730 | B11: Jonas Weber | C11: DE | D11: EUR | E11: 0 | F11: pending_kyc | G11: 45601.5

Sheet fiat_transactions
A1: fiat_order_id | B1: uid | C1: direction | D1: currency | E1: amount | F1: fee | G1: channel | H1: status | I1: created_at | J1: completed_at
A2: fo_20250110_78423190 | B2: 784231905 | C2: deposit | D2: EUR | E2: 1500 | F2: 0 | G2: sepa_instant | H2: completed | I2: 45667.427 | J2: 45667.429
A3: fo_20250220_78423191 | B3: 784231905 | C3: withdrawal | D3: EUR | E3: 500 | F3: 1.5 | G3: sepa_instant | H3: completed | I3: 45708.604 | J3: 45708.608
A4: fo_20250315_78423192 | B4: 784231905 | C4: deposit | D4: EUR | E4: 2000 | F4: 0 | G4: sepa_credit | H4: completed | I4: 45731.375 | J4: 45731.681
A5: fo_20250410_78423193 | B5: 784231905 | C5: withdrawal | D5: EUR | E5: 300 | F5: 1.5 | G5: sepa_instant | H5: failed | I5: 45757.458 | J5: 45757.462
A6: fo_20250112_61590237 | B6: 615902374 | C6: deposit | D6: USD | E6: 50000 | F6: 15 | G6: wire_transfer | H6: completed | I6: 45669.354 | J6: 45669.656
A7: fo_20250214_61590238 | B7: 615902374 | C7: withdrawal | D7: USD | E7: 12000 | F7: 25 | G7: wire_transfer | H7: completed | I7: 45702.99 | J7: 45703.052
A8: fo_20250618_61590239 | B8: 615902374 | C8: withdrawal | D8: USD | E8: 5000 | F8: 25 | G8: wire_transfer | H8: completed | I8: 45826.431 | J8: 45826.59
A9: fo_20250720_61590240 | B9: 615902374 | C9: deposit | D9: USD | E9: 10000 | F9: 15 | G9: wire_transfer | H9: pending | I9: 45858.667
A10: fo_20250308_90317462 | B10: 903174628 | C10: deposit | D10: USD | E10: 1000 | F10: 0 | G10: ach | H10: completed | I10: 45724.382 | J10: 45725.479
A11: fo_20250415_90317463 | B11: 903174628 | C11: withdrawal | D11: USD | E11: 450 | F11: 2 | G11: ach | H11: completed | I11: 45762.583 | J11: 45763.417
A12: fo_20250502_90317464 | B12: 903174628 | C12: withdrawal | D12: USD | E12: 200 | F12: 2 | G12: ach | H12: cancelled | I12: 45779.521
A13: fo_20250418_52840619 | B13: 528406193 | C13: deposit | D13: GBP | E13: 3000 | F13: 0 | G13: faster_payments | H13: completed | I13: 45765.417 | J13: 45765.419
A14: fo_20250525_52840620 | B14: 528406193 | C14: withdrawal | D14: GBP | E14: 800 | F14: 1 | G14: faster_payments | H14: completed | I14: 45802.646 | J14: 45802.648
A15: fo_20250810_52840621 | B15: 528406193 | C15: withdrawal | D15: GBP | E15: 1200 | F15: 1 | G15: faster_payments | H15: completed | I15: 45879.764 | J15: 45879.767
A16: fo_20250912_52840622 | B16: 528406193 | C16: deposit | D16: GBP | E16: 500 | F16: 0 | G16: faster_payments | H16: processing | I16: 45912.385
A17: fo_20250520_84621953 | B17: 846219537 | C17: deposit | D17: EUR | E17: 4200 | F17: 0 | G17: sepa_instant | H17: completed | I17: 45797.465 | J17: 45797.467
A18: fo_20250711_84621954 | B18: 846219537 | C18: deposit | D18: EUR | E18: 1800 | F18: 0 | G18: sepa_credit | H18: completed | I18: 45849.569 | J18: 45849.743
A19: fo_20250605_69248130 | B19: 692481305 | C19: deposit | D19: USD | E19: 25000 | F19: 15 | G19: wire_transfer | H19: completed | I19: 45813.396 | J19: 45813.674
A20: fo_20250915_69248131 | B20: 692481305 | C20: withdrawal | D20: USD | E20: 10000 | F20: 25 | G20: wire_transfer | H20: completed | I20: 45915.583 | J20: 45915.729
A21: fo_20241231_43875092 | B21: 438750921 | C21: deposit | D21: BRL | E21: 2500 | F21: 0 | G21: pix | H21: completed | I21: 45657.993 | J21: 45657.994
A22: fo_20250101_43875093 | B22: 438750921 | C22: withdrawal | D22: BRL | E22: 2500 | F22: 3.5 | G22: pix | H22: completed | I22: 45658.014 | J22: 45658.015
A23: fo_20250901_31958204 | B23: 319582046 | C23: deposit | D23: TRY | E23: 15000 | F23: 0 | G23: papara | H23: completed | I23: 45901.417 | J23: 45901.42
A24: fo_20251010_31958205 | B24: 319582046 | C24: withdrawal | D24: TRY | E24: 6000 | F24: 15 | G24: papara | H24: completed | I24: 45940.597 | J24: 45940.601
A25: fo_20250920_50284719 | B25: 502847193 | C25: withdrawal | D25: USD | E25: 800 | F25: 2 | G25: ach | H25: completed | I25: 45920.698 | J25: 45921.396
A26: fo_20251025_50284720 | B26: 502847193 | C26: withdrawal | D26: USD | E26: 20 | F26: 1 | G26: ach | H26: completed | I26: 45955.458 | J26: 45955.646

Sheet crypto_transactions
A1: crypto_order_id | B1: uid | C1: direction | D1: asset | E1: network | F1: amount | G1: fee | H1: tx_hash | I1: address | J1: status | K1: confirmations | L1: created_at | M1: completed_at
A2: co_20250110_78423190 | B2: 784231905 | C2: deposit | D2: USDT | E2: TRON | F2: 1500 | G2: 0 | H2: 63dd1029e5ca5cf984c2ed338bcba077d3efff2b5d25c543d129490e2588a375 | I2: TZTs2kMxqhLKQUqAiRBqgv1EbiBPk7w2UB | J2: completed | K2: 26 | L2: 45667.472 | M2: 45667.505
A3: co_20250222_78423191 | B3: 784231905 | C3: withdrawal | D3: USDT | E3: TRON | F3: 500 | G3: 1 | H3: 0e641a560a1d663bc5dbc993d5e46d584a2f72554fb1109d97388c553bb651e2 | I3: TBE1SbTMMmmgvA6RbYPBJxmSf2Ytz1xz9L | J3: completed | K3: 20 | L3: 45710.757 | M3: 45710.798
A4: co_20250605_78423192 | B4: 784231905 | C4: deposit | D4: ETH | E4: ETHEREUM | F4: 0.2 | G4: 0 | H4: 0x697857752aaa8607d1961ddfecb3ec44d9fd3cc4c45097ad44c9beff38b5f6a2 | I4: 0xc453f38ebdb4343a3242b060779e7531c69454bc | J4: completed | K4: 25 | L4: 45813.323 | M4: 45813.372
A5: co_20250320_61590237 | B5: 615902374 | C5: deposit | D5: BTC | E5: BITCOIN | F5: 0.05 | G5: 0 | H5: b39506e732fd1f7a288a1ff4338028b098dc9bb0eb37d9145e48440f70849bf5 | I5: bc1q09h5eeyq6xkqfxz35sjdasv4r0uwu7sty56j3q | J5: completed | K5: 15 | L5: 45736.503 | M5: 45736.515
A6: co_20250801_61590238 | B6: 615902374 | C6: withdrawal | D6: BTC | E6: BITCOIN | F6: 0.02 | G6: 0.0002 | H6: 3aad3f0cdb66295a3bd2cc2a65eb900b3d1662a4388bbf093fb4593da315fad8 | I6: bc1q3glu088led8nf7j4puhy6sj4x63tfz0vypclkn | J6: completed | K6: 14 | L6: 45870.688 | M6: 45870.694
A7: co_20250815_61590239 | B7: 615902374 | C7: deposit | D7: USDT | E7: BSC | F7: 600 | G7: 0 | H7: 0xa19ab825bc70785a4762c5d0704d338de601f635364658929267aa7365da4400 | I7: 0x6e0a0adb598ac01b4a24cca74747862290c52668 | J7: completed | K7: 25 | L7: 45884.378 | M7: 45884.404
A8: co_20250212_90317462 | B8: 903174628 | C8: deposit | D8: USDT | E8: ARBITRUM | F8: 400 | G8: 0 | H8: 0xb933b56829a298cdc0afd793e79c16011ac1fb6fa5fa00ffe25f4e971e59dfbd | I8: 0xdc3487818cfda4ea4a05c495791f680aecf9d8b3 | J8: completed | K8: 26 | L8: 45700.569 | M8: 45700.576
A9: co_20250902_90317463 | B9: 903174628 | C9: withdrawal | D9: USDT | E9: BSC | F9: 300 | G9: 0.8 | H9: 0xea0f2bd3d9dc5ed8def5298f1c68cbe8782ec64d7e6815d0c7e018d73345af38 | I9: 0x4413ae3344245ba4bd12d2b473b9c642132ce2e5 | J9: completed | K9: 17 | L9: 45902.431 | M9: 45902.474
A10: co_20251220_90317464 | B10: 903174628 | C10: withdrawal | D10: USDT | E10: ARBITRUM | F10: 250 | G10: 0.3 | I10: 0x3b13a19c9377fe05031c01098a19ac18966a548f | J10: processing | K10: 0 | L10: 46011.84
A11: co_20250407_52840619 | B11: 528406193 | C11: withdrawal | D11: USDT | E11: ETHEREUM | F11: 1500 | G11: 5 | H11: 0x76dee5dcb35703c649a43288fc14e2cf692bc9821031877df211823bd509e148 | I11: 0x49d045820e74c6588e1a0c26757aaef2476c22ff | J11: completed | K11: 23 | L11: 45754.885 | M11: 45754.89
A12: co_20250420_52840620 | B12: 528406193 | C12: deposit | D12: USDT | E12: TRON | F12: 700 | G12: 0 | H12: e1bd98dde29c160c154b642a90fc3cc5fa29ffd2da05c2fa35d35fb8bee1e5a3 | I12: TBGKnRW9K5wiLmhUDSLsUXJuK5ETvC83xM | J12: completed | K12: 23 | L12: 45767.365 | M12: 45767.419
A13: co_20251111_52840621 | B13: 528406193 | C13: withdrawal | D13: USDT | E13: TRON | F13: 300 | G13: 1 | H13: b0b316bd299eee088bcdf1ae9328dd1c899294f77a63ab6a4887817e91c53ed3 | I13: TMn9NxEKnutzexB6W3kKLbfzsLuRw9ocut | J13: completed | K13: 21 | L13: 45972.545 | M13: 45972.548
A14: co_20250105_84621953 | B14: 846219537 | C14: deposit | D14: ETH | E14: ETHEREUM | F14: 0.4 | G14: 0 | H14: 0x0d28c056661be39b220f2c211e59a5ee51db5186d5ab9629d69ee2cc89d6dfb0 | I14: 0x099c0e97614fd374d7e546dc2fcbdd52df00224a | J14: completed | K14: 15 | L14: 45662.267 | M14: 45662.324
A15: co_20250505_84621954 | B15: 846219537 | C15: withdrawal | D15: ETH | E15: ETHEREUM | F15: 0.1 | G15: 0.0012 | H15: 0xea497e8d88ee3ee055bd364c2e146246bb96deb5dc86f9c5505c3b292eb85b80 | I15: 0x41108ae1113dc504a0f34c39d731ac814c343b9b | J15: completed | K15: 26 | L15: 45782.719 | M15: 45782.748
A16: co_20251010_84621955 | B16: 846219537 | C16: deposit | D16: USDT | E16: TRON | F16: 1000 | G16: 0 | H16: 6417aedbf3a07badbd672209b43886240cf096b9015d44cc53ca179b33577279 | I16: TSEdPbLdvpu7xY9sKwGuRPLpU5BuaCqjza | J16: completed | K16: 27 | L16: 45940.375 | M16: 45940.409
A17: co_20250107_69248130 | B17: 692481305 | C17: deposit | D17: USDT | E17: TRON | F17: 2000 | G17: 0 | H17: 360e42a95096a44553f9b6ac51a889d7355a8a472968bbc6865573e9ced82456 | I17: TzSQmX1NuEsYWRaskDpkqVxaUtRMQ3Hrqf | J17: completed | K17: 21 | L17: 45664.604 | M17: 45664.628
A18: co_20250318_69248131 | B18: 692481305 | C18: withdrawal | D18: USDT | E18: TRON | F18: 600 | G18: 1 | H18: d62970a686c4901f7776dd175ff0053d1af520e991121a082a88f51bcdde9637 | I18: TdwuvV9ytQqruGcwsJcaR2SHdztSJAfztM | J18: completed | K18: 22 | L18: 45734.486 | M18: 45734.542
A19: co_20250709_69248132 | B19: 692481305 | C19: deposit | D19: BTC | E19: BITCOIN | F19: 0.03 | G19: 0 | H19: b811a6d96346cb2407724c1b86fac4357b0bb24a64938fff77c0214f00389e0b | I19: bc1q76tcqtgmgd0gdw7v0ujpnt4w929j8kc5kznj9e | J19: completed | K19: 7 | L19: 45847.809 | M19: 45847.867
A20: co_20250801_69248133 | B20: 692481305 | C20: deposit | D20: USDT | E20: BSC | F20: 500 | G20: 0 | H20: 0x33aeea111548a4bef60d04849b6326c2562a08a7de68b0f248e8e3f9de93af63 | I20: 0x29c14b9b9823aa3754bc21f9c4dfbe252491d85e | J20: confirming | K20: 5 | L20: 45870.34
A21: co_20251201_69248134 | B21: 692481305 | C21: withdrawal | D21: USDT | E21: BSC | F21: 300 | G21: 0.8 | I21: 0xe0b6b8387d822451eca3c2173d974ef5bf2c6fbb | J21: failed | K21: 0 | L21: 45992.306
A22: co_20241231_43875092 | B22: 438750921 | C22: deposit | D22: USDT | E22: TRON | F22: 300 | G22: 0 | H22: 233ee1f098f65a8b6832253005919d0086745c9ec55a04c7c4f8fd1b01b46b52 | I22: TvcdwQMYE3CJ1uBT2jN5cSfNmwwyGz4syK | J22: completed | K22: 26 | L22: 45657.986 | M22: 45657.997
A23: co_20250101_43875093 | B23: 438750921 | C23: deposit | D23: USDT | E23: TRON | F23: 500 | G23: 0 | H23: a604c6354367ee9df63fa4a8e4c9ac51a954ea3e2b9bf929c991345fcd6c4fc8 | I23: T9gb744yUqjdkiaJCGLnugKmjXSsUpCb4r | J23: completed | K23: 25 | L23: 46023.01 | M23: 46023.036
A24: co_20251229_43875094 | B24: 438750921 | C24: deposit | D24: USDT | E24: TRON | F24: 1000 | G24: 0 | H24: 7d0161907f296b3ab768712f56095ba777ac7536d241896d3a7b53fbaaa460b6 | I24: Tvtb4VirWCMnbBktzqaCvboDmo9rSzo7nh | J24: completed | K24: 25 | L24: 46020.382 | M24: 46020.398
A25: co_20251231_43875095 | B25: 438750921 | C25: withdrawal | D25: USDT | E25: TRON | F25: 1800 | G25: 1 | H25: 219361f01e2a7c60f65ca604af06a392872684ff230241b3823a9540e645df54 | I25: TVSzNFcdNHjGcWNzbVi7movAKU9vDEUg3J | J25: completed | K25: 34 | L25: 46022.51 | M25: 46022.546
A26: co_20251105_31958204 | B26: 319582046 | C26: deposit | D26: BTC | E26: BITCOIN | F26: 0.001 | G26: 0 | H26: e48440f70849bf5b39506e732fd1f7a288a1ff4338028b098dc9bb0eb37d9145 | I26: bc1q9d846392019485720192847291048572019283 | J26: completed | K26: 6 | L26: 45966.59 | M26: 45966.622

Sheet exchange_rates
A1: asset | B1: asset_name | C1: asset_type | D1: quote_currency | E1: rate_to_usdt | F1: usdt_to_asset_rate | G1: effective_date | H1: source
A2: USDT | B2: Tether USD | C2: Crypto | D2: USDT | E2: 1 | F2: =IFERROR(1/E2, 0) -> 1 | G2: 45536 | H2: 1:1 Pegged Baseline
A3: BTC | B3: Bitcoin | C3: Crypto | D3: USDT | E3: 64500 | F3: =IFERROR(1/E3, 0) -> 1.5503876e-05 | G3: 45536 | H3: Binance / CoinGecko Benchmark
A4: ETH | B4: Ethereum | C4: Crypto | D4: USDT | E4: 2650 | F4: =IFERROR(1/E4, 0) -> 0.00037735849 | G4: 45536 | H4: Binance / CoinGecko Benchmark
A5: USD | B5: US Dollar | C5: Fiat | D5: USDT | E5: 1 | F5: =IFERROR(1/E5, 0) -> 1 | G5: 45536 | H5: ECB / Federal Reserve Benchmark
A6: EUR | B6: Euro | C6: Fiat | D6: USDT | E6: 1.085 | F6: =IFERROR(1/E6, 0) -> 0.92165899 | G6: 45536 | H6: ECB Reference Rate
A7: GBP | B7: British Pound | C7: Fiat | D7: USDT | E7: 1.285 | F7: =IFERROR(1/E7, 0) -> 0.77821012 | G7: 45536 | H7: Bank of England Reference Rate
A8: BRL | B8: Brazilian Real | C8: Fiat | D8: USDT | E8: 0.182 | F8: =IFERROR(1/E8, 0) -> 5.4945055 | G8: 45536 | H8: Central Bank of Brazil Benchmark
A9: TRY | B9: Turkish Lira | C9: Fiat | D9: USDT | E9: 0.0295 | F9: =IFERROR(1/E9, 0) -> 33.898305 | G9: 45536 | H9: Central Bank of Turkey Benchmark

Sheet expected_fiat_result
A1: uid | B1: currency | C1: deposit_amount | D1: withdrawal_amount | E1: net_amount
A2: 784231905 | B2: EUR | C2: 3500 | D2: 500 | E2: =C2-D2 -> 3000
A3: 615902374 | B3: USD | C3: 50000 | D3: 17000 | E3: =C3-D3 -> 33000
A4: 903174628 | B4: USD | C4: 1000 | D4: 450 | E4: =C4-D4 -> 550
A5: 528406193 | B5: GBP | C5: 3000 | D5: 2000 | E5: =C5-D5 -> 1000
A6: 846219537 | B6: EUR | C6: 6000 | D6: 0 | E6: =C6-D6 -> 6000
A7: 692481305 | B7: USD | C7: 25000 | D7: 10000 | E7: =C7-D7 -> 15000
A8: 438750921 | B8: BRL | C8: 2500 | D8: 2500 | E8: =C8-D8 -> 0
A9: 319582046 | B9: TRY | C9: 15000 | D9: 6000 | E9: =C9-D9 -> 9000
A10: 502847193 | B10: USD | C10: 0 | D10: 820 | E10: =C10-D10 -> -820

Sheet expected_crypto_result
A1: uid | B1: asset | C1: network | D1: deposit_amount | E1: withdrawal_amount | F1: net_amount
A2: 784231905 | B2: USDT | C2: TRON | D2: 1500 | E2: 500 | F2: =D2-E2 -> 1000
A3: 784231905 | B3: ETH | C3: ETHEREUM | D3: 0.2 | E3: 0 | F3: =D3-E3 -> 0.2
A4: 615902374 | B4: BTC | C4: BITCOIN | D4: 0.05 | E4: 0.02 | F4: =D4-E4 -> 0.03
A5: 615902374 | B5: USDT | C5: BSC | D5: 600 | E5: 0 | F5: =D5-E5 -> 600
A6: 903174628 | B6: USDT | C6: ARBITRUM | D6: 400 | E6: 0 | F6: =D6-E6 -> 400
A7: 903174628 | B7: USDT | C7: BSC | D7: 0 | E7: 300 | F7: =D7-E7 -> -300
A8: 528406193 | B8: USDT | C8: ETHEREUM | D8: 0 | E8: 1500 | F8: =D8-E8 -> -1500
A9: 528406193 | B9: USDT | C9: TRON | D9: 700 | E9: 300 | F9: =D9-E9 -> 400
A10: 846219537 | B10: ETH | C10: ETHEREUM | D10: 0.4 | E10: 0.1 | F10: =D10-E10 -> 0.3
A11: 846219537 | B11: USDT | C11: TRON | D11: 1000 | E11: 0 | F11: =D11-E11 -> 1000
A12: 692481305 | B12: USDT | C12: TRON | D12: 2000 | E12: 600 | F12: =D12-E12 -> 1400
A13: 692481305 | B13: BTC | C13: BITCOIN | D13: 0.03 | E13: 0 | F13: =D13-E13 -> 0.03
... A15: 319582046 | B15: BTC | C15: BITCOIN | D15: 0.001 | E15: 0 | F15: =D15-E15 -> 0.001

Sheet data_rules
A1: rule_id | B1: table_name | C1: column_name | D1: data_type | E1: is_nullable | F1: is_unique | G1: allowed_values_or_pattern | H1: foreign_key | I1: business_rule_description
A2: R_USR_01 | B2: users | C2: uid | D2: BIGINT | E2: NO | F2: YES | G2: ^[1-9][0-9]{8}$ | H2: PK | I2: 用户表主键；必须为唯一的9位数字标识符。
A3: R_USR_02 | B3: users | C3: user_name | D3: VARCHAR | E3: NO | F3: NO | G3: ^[A-Za-z ]+$ | H3: - | I3: 账户持有人的法定全名。
A4: R_USR_03 | B4: users | C4: country_code | D4: VARCHAR(2) | E4: NO | F4: NO | G4: ISO 3166-1 alpha-2 标准二字码（如 US, DE, JP, GB, FR, AE, BR, TR, KR） | H4: - | I4: 用户常住地国家/地区二字码（ISO 3166-1）。
A5: R_USR_04 | B5: users | C5: base_fiat_currency | D5: VARCHAR(3) | E5: NO | F5: NO | G5: EUR, USD, GBP, BRL, TRY | H5: - | I5: 与用户画像关联的主要本地法币币种。
A6: R_USR_05 | B6: users | C6: kyc_level | D6: INTEGER | E6: NO | F6: NO | G6: 0, 1, 2, 3 | H6: - | I6: 合规身份认证等级（0=未认证，1=基础认证，2=中级认证，3=高级认证）。
A7: R_USR_06 | B7: users | C7: account_status | D7: VARCHAR | E7: NO | F7: NO | G7: active, frozen, pending_kyc, closed | H7: - | I7: 用户账户的当前运营与合规状态。
A8: R_USR_07 | B8: users | C8: created_at | D8: TIMESTAMP | E8: NO | F8: NO | G8: YYYY-MM-DD HH:MM:SS | H8: - | I8: 用户注册时间戳；必须早于该用户的任何交易时间戳。
A9: R_FIA_01 | B9: fiat_transactions | C9: fiat_order_id | D9: VARCHAR | E9: NO | F9: YES | G9: ^fo_[0-9]{8}_[a-z0-9]{8}$ | H9: PK | I9: 法币交易表主键；以 fo_ 开头的固定20位唯一标识符。
A10: R_FIA_02 | B10: fiat_transactions | C10: uid | D10: BIGINT | E10: NO | F10: NO | G10: ^[1-9][0-9]{8}$ | H10: users.uid | I10: 外键关联有效用户；对应值必须存在于 users 表中。
A11: R_FIA_03 | B11: fiat_transactions | C11: direction | D11: VARCHAR | E11: NO | F11: NO | G11: deposit, withdrawal | H11: - | I11: 相对于交易所托管资金的资金流向（充值/提现）。
A12: R_FIA_04 | B12: fiat_transactions | C12: currency | D12: VARCHAR(3) | E12: NO | F12: NO | G12: EUR, USD, GBP, BRL, TRY | H12: - | I12: ISO 标准法币币种代码；严禁与加密货币资产混淆。
... A28: R_CRY_10 | B28: crypto_transactions | C28: status | D28: VARCHAR | E28: NO | F28: NO | G28: completed, confirming, processing, failed, cancelled | H28: - | I28: 转账生命周期状态；仅 'completed'（已完成）订单计入预期加密净额汇总。

Sheet qa_result
A1: check_id | B1: check_type | C1: table_name | D1: rule | E1: result | F1: affected_rows | G1: severity | H1: details
A2: CHK_SCH_01 | B2: Schema Check | C2: users | D2: 校验必填列字段名完整性及下划线小写命名规范（snake_case） | E2: PASSED | F2: 0 | G2: BLOCKER | H2: 全部 7 个字段均存在且符合 lower_snake_case 规范。
A3: CHK_SCH_02 | B3: Schema Check | C3: fiat_transactions | D3: 校验必填列字段名完整性及下划线小写命名规范（snake_case） | E3: PASSED | F3: 0 | G3: BLOCKER | H3: 全部 10 个字段均存在且符合 lower_snake_case 规范。
A4: CHK_SCH_03 | B4: Schema Check | C4: crypto_transactions | D4: 校验必填列字段名完整性及下划线小写命名规范（snake_case） | E4: PASSED | F4: 0 | G4: BLOCKER | H4: 全部 13 个字段均存在且符合 lower_snake_case 规范。
A5: CHK_CMP_01 | B5: Completeness Check | C5: users | D5: 校验非空列是否存在空值（NULL）或空白单元格 | E5: PASSED | F5: 0 | G5: CRITICAL | H5: 在 uid、user_name、country_code、base_fiat_currency、kyc_level、account_status、created_at 中均未检测到空值（0 个空值）。
A6: CHK_CMP_02 | B6: Completeness Check | C6: fiat_transactions | D6: 校验非空列是否存在空值（NULL）或空白单元格 | E6: PASSED | F6: 0 | G6: CRITICAL | H6: 所有必填字段均无空值；completed_at 仅在非完成状态（non-completed）记录中允许为空。
A7: CHK_CMP_03 | B7: Completeness Check | C7: crypto_transactions | D7: 校验非空列是否存在空值（NULL）或空白单元格 | E7: PASSED | F7: 0 | G7: CRITICAL | H7: 所有必填字段均无空值；tx_hash 与 completed_at 仅在处理中或失败的转账中允许为空。
A8: CHK_UNI_01 | B8: Uniqueness Check | C8: users | D8: 确保主键 uid 全局唯一无重复 | E8: PASSED | F8: 0 | G8: CRITICAL | H8: 10 条记录包含 10 个唯一 UID，未发现重复主键。
A9: CHK_UNI_02 | B9: Uniqueness Check | C9: fiat_transactions | D9: 确保主键 fiat_order_id 全局唯一无重复 | E9: PASSED | F9: 0 | G9: CRITICAL | H9: 25 条记录包含 25 个唯一订单 ID，未发现重复主键。
A10: CHK_UNI_03 | B10: Uniqueness Check | C10: crypto_transactions | D10: 确保主键 crypto_order_id 全局唯一无重复 | E10: PASSED | F10: 0 | G10: CRITICAL | H10: 25 条记录包含 25 个唯一订单 ID，未发现重复主键。
A11: CHK_REF_01 | B11: Referential Integrity | C11: fiat_transactions | D11: 校验外键 uid 是否均引用有效的 users.uid | E11: PASSED | F11: 0 | G11: CRITICAL | H11: 全部 25 条法币交易记录均成功关联 users 表中的现有用户画像。
A12: CHK_REF_02 | B12: Referential Integrity | C12: crypto_transactions | D12: 校验外键 uid 是否均引用有效的 users.uid | E12: PASSED | F12: 0 | G12: CRITICAL | H12: 全部 25 条加密交易记录均成功关联 users 表中的现有用户画像。
A13: CHK_VAL_01 | B13: Validity Check | C13: fiat_transactions | D13: 校验资金流向、币种、渠道、状态等枚举值合规性及交易金额为正数 | E13: PASSED | F13: 0 | G13: HIGH | H13: 资金流向、状态与币种均完全符合数据规则，所有金额均严格大于 0。
... A18: CHK_REC_02 | B18: Reconciliation Check | C18: expected_crypto_result | D18: 重新从 crypto_transactions 计算 SQL 聚合值并与基准对照表核对 | E18: PASSED | F18: 0 | G18: BLOCKER | H18: 原始已完成交易汇总与 expected_crypto_result 基准表在全部 14 个用户-资产-主网分组中达到 100% 完全匹配。

Sheet fix_log
A1: fix_id | B1: issue_description | C1: root_cause | D1: affected_table_and_records | E1: corrective_action | F1: regression_status | G1: verified_by
A2: FIX_001 | B2: 历史架构中存在大写和带连字符的非标交易 ID | C2: 历史数据表采用非统一 ID 规则，缺乏明确的业务域前缀 | D2: fiat_transactions 与 crypto_transactions 表 | E2: 将所有法币订单 ID 统一标准化为 fo_YYYYMMDD_<hex>，加密订单 ID 统一为 co_YYYYMMDD_<hex>，强制实行固定长度与业务域隔离 | F2: 已通过 (PASSED) | G2: Automated QA (CHK_UNI_02, CHK_UNI_03)
A3: FIX_002 | B3: 跨币种混同估值汇总违规 | C3: 旧表将所有资产折算为估算的 amount_usdt_equiv，并在不同法币和加密货币之间直接混同累加 | D3: onchain_transfers 表（amount_usdt_equiv 字段） | E3: 彻底消除跨币种混合汇总；建立严格的多维聚合分区：法币按 uid + currency，加密货币按 uid + asset + network | F3: 已通过 (PASSED) | G3: DuckDB SQL Benchmark Verification
A4: FIX_003 | B4: 资金流汇总统计中错误包含了非最终态交易 | C4: 处理中（pending/processing）的订单易被未添加状态过滤器的简单 SUM() 查询误计入 | D4: fiat_transactions 与 crypto_transactions 表 | E4: 在预期基准模型中强制执行严格的生命周期状态过滤（WHERE status = 'completed'），并补充明确的处理中与失败用例测试 | F4: 已通过 (PASSED) | G4: Automated QA (CHK_REC_01, CHK_REC_02)
A5: FIX_004 | B5: 区块链充值入账时的网络手续费扣减逻辑不一致 | C5: 从外部钱包充值时，接收方交易所不应在入账时扣除用户的 Gas 手续费 | D5: crypto_transactions 表 | E5: 将所有充值记录的手续费归一化为 0.00；手续费仅在用户发起提现广播时严格计收 | F5: 已通过 (PASSED) | G5: Automated QA (CHK_VAL_02)
A6: FIX_005 | B6: 潜在的时间时序反转异常（结算时间早于订单创建时间） | C6: 合成数据中无约束的时间戳生成逻辑可能导致 completed_at < created_at | D6: fiat_transactions 与 crypto_transactions 表 | E6: 部署严格的校验约束逻辑，确保所有历史记录中 completed_at >= created_at 严格成立 | F6: 已通过 (PASSED) | G6: Automated QA (CHK_LOG_01, CHK_LOG_02)

Sheet _backup_20260924_111845
B2: 交易所资金流向与业务风控全局决策看板 (Executive Funds Flow & Risk Monitor) | P2: 看板数据层 · 月度出入金与净流入序列 (Monthly Flow Aggregation)
B3: 监控周期: 2024Q4 - 2025Q4 | 质检状态: 🟢 核心规则全部合规 (17/17 QA Checks Passed) | 预警等级: ⚠️ 发现冻结用户出金与网络挂起风险 | P3: 月份 (Month) | Q3: 充值入金 (Deposit) | R3: 提现出金 (Withdrawal) | S3: 净沉淀额 (Net Inflow)
P4: =DATE(2024, 12, 1) -> 45627 | Q4: =SUMIFS(fiat_transactions!$E$2:$E$26, fiat_transactions!$D$2:$D$26, "USD", fiat_transactions!$C$2:$C$26, "deposit", fiat_transactions!$H$2:$H$26, "completed", fiat_transactions!$I$2:$I$26, ">="&$P4, fiat_transactions!$I$2:$I$26, "<"&EDATE($P4, 1)) + SUMIFS(crypto_transactions!$F$2:$F$26, crypto_transactions!$D$2:$D$26, "USDT", crypto_transactions!$C$2:$C$26, "deposit", crypto_transactions!$J$2:$J$26, "completed", crypto_transactions!$L$2:$L$26, ">="&$P4, crypto_transactions!$L$2:$L$26, "<"&EDATE($P4, 1)) -> 300 | R4: =SUMIFS(fiat_transactions!$E$2:$E$26, fiat_transactions!$D$2:$D$26, "USD", fiat_transactions!$C$2:$C$26, "withdrawal", fiat_transactions!$H$2:$H$26, "completed", fiat_transactions!$I$2:$I$26, ">="&$P4, fiat_transactions!$I$2:$I$26, "<"&EDATE($P4, 1)) + SUMIFS(crypto_transactions!$F$2:$F$26, crypto_transactions!$D$2:$D$26, "USDT", crypto_transactions!$C$2:$C$26, "withdrawal", crypto_transactions!$J$2:$J$26, "completed", crypto_transactions!$L$2:$L$26, ">="&$P4, crypto_transactions!$L$2:$L$26, "<"&EDATE($P4, 1)) -> 0 | S4: =Q4-R4 -> 300
B5: 法币核心总流水 (USD GMV) | E5: 链上核心总流水 (USDT GMV) | I5: 全局订单履约成功率 | L5: 法币核心净沉淀 (USD Net Inflow) | P5: =DATE(2025, 1, 1) -> 45658 | Q5: =SUMIFS(fiat_transactions!$E$2:$E$26, fiat_transactions!$D$2:$D$26, "USD", fiat_transactions!$C$2:$C$26, "deposit", fiat_transactions!$H$2:$H$26, "completed", fiat_transactions!$I$2:$I$26, ">="&$P5, fiat_transactions!$I$2:$I$26, "<"&EDATE($P5, 1)) + SUMIFS(crypto_transactions!$F$2:$F$26, crypto_transactions!$D$2:$D$26, "USDT", crypto_transactions!$C$2:$C$26, "deposit", crypto_transactions!$J$2:$J$26, "completed", crypto_transactions!$L$2:$L$26, ">="&$P5, crypto_transactions!$L$2:$L$26, "<"&EDATE($P5, 1)) -> 53500 | R5: =SUMIFS(fiat_transactions!$E$2:$E$26, fiat_transactions!$D$2:$D$26, "USD", fiat_transactions!$C$2:$C$26, "withdrawal", fiat_transactions!$H$2:$H$26, "completed", fiat_transactions!$I$2:$I$26, ">="&$P5, fiat_transactions!$I$2:$I$26, "<"&EDATE($P5, 1)) + SUMIFS(crypto_transactions!$F$2:$F$26, crypto_transactions!$D$2:$D$26, "USDT", crypto_transactions!$C$2:$C$26, "withdrawal", crypto_transactions!$J$2:$J$26, "completed", crypto_transactions!$L$2:$L$26, ">="&$P5, crypto_transactions!$L$2:$L$26, "<"&EDATE($P5, 1)) -> 0 | S5: =Q5-R5 -> 53500
B6: =SUMIFS(fiat_transactions!E2:E26, fiat_transactions!D2:D26, "USD", fiat_transactions!H2:H26, "completed") -> 104270 | E6: =SUMIFS(crypto_transactions!F2:F26, crypto_transactions!D2:D26, "USDT", crypto_transactions!J2:J26, "completed") -> 13000 | I6: =(COUNTIF(fiat_transactions!H2:H26, "completed") + COUNTIF(crypto_transactions!J2:J26, "completed")) / (COUNTA(fiat_transactions!H2:H26) + COUNTA(crypto_transactions!J2:J26)) -> 0.86 | L6: =SUMIFS(fiat_transactions!E2:E26, fiat_transactions!D2:D26, "USD", fiat_transactions!C2:C26, "deposit", fiat_transactions!H2:H26, "completed") - SUMIFS(fiat_transactions!E2:E26, fiat_transactions!D2:D26, "USD", fiat_transactions!C2:C26, "withdrawal", fiat_transactions!H2:H26, "completed") -> 47730 | P6: =DATE(2025, 2, 1) -> 45689 | Q6: =SUMIFS(fiat_transactions!$E$2:$E$26, fiat_transactions!$D$2:$D$26, "USD", fiat_transactions!$C$2:$C$26, "deposit", fiat_transactions!$H$2:$H$26, "completed", fiat_transactions!$I$2:$I$26, ">="&$P6, fiat_transactions!$I$2:$I$26, "<"&EDATE($P6, 1)) + SUMIFS(crypto_transactions!$F$2:$F$26, crypto_transactions!$D$2:$D$26, "USDT", crypto_transactions!$C$2:$C$26, "deposit", crypto_transactions!$J$2:$J$26, "completed", crypto_transactions!$L$2:$L$26, ">="&$P6, crypto_transactions!$L$2:$L$26, "<"&EDATE($P6, 1)) -> 400 | R6: =SUMIFS(fiat_transactions!$E$2:$E$26, fiat_transactions!$D$2:$D$26, "USD", fiat_transactions!$C$2:$C$26, "withdrawal", fiat_transactions!$H$2:$H$26, "completed", fiat_transactions!$I$2:$I$26, ">="&$P6, fiat_transactions!$I$2:$I$26, "<"&EDATE($P6, 1)) + SUMIFS(crypto_transactions!$F$2:$F$26, crypto_transactions!$D$2:$D$26, "USDT", crypto_transactions!$C$2:$C$26, "withdrawal", crypto_transactions!$J$2:$J$26, "completed", crypto_transactions!$L$2:$L$26, ">="&$P6, crypto_transactions!$L$2:$L$26, "<"&EDATE($P6, 1)) -> 12500 | S6: =Q6-R6 -> -12100
B7: ="已完成 9 笔 USD / 全币种 21 笔" -> 已完成 9 笔 USD / 全币种 21 笔 | E7: ="已完成 15 笔 USDT / 覆盖 4 大公链" -> 已完成 15 笔 USDT / 覆盖 4 大公链 | I7: ="43 笔成功 / 7 笔异常或挂起" -> 43 笔成功 / 7 笔异常或挂起 | L7: ="充值 $76,000 | 提现 $18,270" -> 充值 $76,000 | 提现 $18,270 | P7: =DATE(2025, 3, 1) -> 45717 | Q7: =SUMIFS(fiat_transactions!$E$2:$E$26, fiat_transactions!$D$2:$D$26, "USD", fiat_transactions!$C$2:$C$26, "deposit", fiat_transactions!$H$2:$H$26, "completed", fiat_transactions!$I$2:$I$26, ">="&$P7, fiat_transactions!$I$2:$I$26, "<"&EDATE($P7, 1)) + SUMIFS(crypto_transactions!$F$2:$F$26, crypto_transactions!$D$2:$D$26, "USDT", crypto_transactions!$C$2:$C$26, "deposit", crypto_transactions!$J$2:$J$26, "completed", crypto_transactions!$L$2:$L$26, ">="&$P7, crypto_transactions!$L$2:$L$26, "<"&EDATE($P7, 1)) -> 1000 | R7: =SUMIFS(fiat_transactions!$E$2:$E$26, fiat_transactions!$D$2:$D$26, "USD", fiat_transactions!$C$2:$C$26, "withdrawal", fiat_transactions!$H$2:$H$26, "completed", fiat_transactions!$I$2:$I$26, ">="&$P7, fiat_transactions!$I$2:$I$26, "<"&EDATE($P7, 1)) + SUMIFS(crypto_transactions!$F$2:$F$26, crypto_transactions!$D$2:$D$26, "USDT", crypto_transactions!$C$2:$C$26, "withdrawal", crypto_transactions!$J$2:$J$26, "completed", crypto_transactions!$L$2:$L$26, ">="&$P7, crypto_transactions!$L$2:$L$26, "<"&EDATE($P7, 1)) -> 600 | S7: =Q7-R7 -> 400
B8: ="通道手续费创收: $" & TEXT(SUM(fiat_transactions!F2:F26), "0.00") -> 通道手续费创收: $150.50 | E8: ="链上手续费创收: " & TEXT(SUMIFS(crypto_transactions!G2:G26, crypto_transactions!D2:D26, "USDT"), "0.00") & " USDT" -> 链上手续费创收: 10.90 USDT | I8: ="质检合规率: 100% (17/17 项规则)" -> 质检合规率: 100% (17/17 项规则) | L8: ="USDT 净沉淀: +3,000.00 USDT" -> USDT 净沉淀: +3,000.00 USDT | P8: =DATE(2025, 4, 1) -> 45748 | Q8: =SUMIFS(fiat_transactions!$E$2:$E$26, fiat_transactions!$D$2:$D$26, "USD", fiat_transactions!$C$2:$C$26, "deposit", fiat_transactions!$H$2:$H$26, "completed", fiat_transactions!$I$2:$I$26, ">="&$P8, fiat_transactions!$I$2:$I$26, "<"&EDATE($P8, 1)) + SUMIFS(crypto_transactions!$F$2:$F$26, crypto_transactions!$D$2:$D$26, "USDT", crypto_transactions!$C$2:$C$26, "deposit", crypto_transactions!$J$2:$J$26, "completed", crypto_transactions!$L$2:$L$26, ">="&$P8, crypto_transactions!$L$2:$L$26, "<"&EDATE($P8, 1)) -> 700 | R8: =SUMIFS(fiat_transactions!$E$2:$E$26, fiat_transactions!$D$2:$D$26, "USD", fiat_transactions!$C$2:$C$26, "withdrawal", fiat_transactions!$H$2:$H$26, "completed", fiat_transactions!$I$2:$I$26, ">="&$P8, fiat_transactions!$I$2:$I$26, "<"&EDATE($P8, 1)) + SUMIFS(crypto_transactions!$F$2:$F$26, crypto_transactions!$D$2:$D$26, "USDT", crypto_transactions!$C$2:$C$26, "withdrawal", crypto_transactions!$J$2:$J$26, "completed", crypto_transactions!$L$2:$L$26, ">="&$P8, crypto_transactions!$L$2:$L$26, "<"&EDATE($P8, 1)) -> 1950 | S8: =Q8-R8 -> -1250
P9: =DATE(2025, 5, 1) -> 45778 | Q9: =SUMIFS(fiat_transactions!$E$2:$E$26, fiat_transactions!$D$2:$D$26, "USD", fiat_transactions!$C$2:$C$26, "deposit", fiat_transactions!$H$2:$H$26, "completed", fiat_transactions!$I$2:$I$26, ">="&$P9, fiat_transactions!$I$2:$I$26, "<"&EDATE($P9, 1)) + SUMIFS(crypto_transactions!$F$2:$F$26, crypto_transactions!$D$2:$D$26, "USDT", crypto_transactions!$C$2:$C$26, "deposit", crypto_transactions!$J$2:$J$26, "completed", crypto_transactions!$L$2:$L$26, ">="&$P9, crypto_transactions!$L$2:$L$26, "<"&EDATE($P9, 1)) -> 0 | R9: =SUMIFS(fiat_transactions!$E$2:$E$26, fiat_transactions!$D$2:$D$26, "USD", fiat_transactions!$C$2:$C$26, "withdrawal", fiat_transactions!$H$2:$H$26, "completed", fiat_transactions!$I$2:$I$26, ">="&$P9, fiat_transactions!$I$2:$I$26, "<"&EDATE($P9, 1)) + SUMIFS(crypto_transactions!$F$2:$F$26, crypto_transactions!$D$2:$D$26, "USDT", crypto_transactions!$C$2:$C$26, "withdrawal", crypto_transactions!$J$2:$J$26, "completed", crypto_transactions!$L$2:$L$26, ">="&$P9, crypto_transactions!$L$2:$L$26, "<"&EDATE($P9, 1)) -> 0 | S9: =Q9-R9 -> 0
B10: 💵 多币种出入金与流动性分析 (Fiat & Crypto Liquidity Net Flow) | I10: ⚡ 结算通道与公链网络稳定性监控 (Channel & Network Reliability) | P10: =DATE(2025, 6, 1) -> 45809 | Q10: =SUMIFS(fiat_transactions!$E$2:$E$26, fiat_transactions!$D$2:$D$26, "USD", fiat_transactions!$C$2:$C$26, "deposit", fiat_transactions!$H$2:$H$26, "completed", fiat_transactions!$I$2:$I$26, ">="&$P10, fiat_transactions!$I$2:$I$26, "<"&EDATE($P10, 1)) + SUMIFS(crypto_transactions!$F$2:$F$26, crypto_transactions!$D$2:$D$26, "USDT", crypto_transactions!$C$2:$C$26, "deposit", crypto_transactions!$J$2:$J$26, "completed", crypto_transactions!$L$2:$L$26, ">="&$P10, crypto_transactions!$L$2:$L$26, "<"&EDATE($P10, 1)) -> 25000 | R10: =SUMIFS(fiat_transactions!$E$2:$E$26, fiat_transactions!$D$2:$D$26, "USD", fiat_transactions!$C$2:$C$26, "withdrawal", fiat_transactions!$H$2:$H$26, "completed", fiat_transactions!$I$2:$I$26, ">="&$P10, fiat_transactions!$I$2:$I$26, "<"&EDATE($P10, 1)) + SUMIFS(crypto_transactions!$F$2:$F$26, crypto_transactions!$D$2:$D$26, "USDT", crypto_transactions!$C$2:$C$26, "withdrawal", crypto_transactions!$J$2:$J$26, "completed", crypto_transactions!$L$2:$L$26, ">="&$P10, crypto_transactions!$L$2:$L$26, "<"&EDATE($P10, 1)) -> 5000 | S10: =Q10-R10 -> 20000
B11: 资产 / 币种 | C11: 资产类别 | D11: 充值入金 (Deposit) | E11: 提现出金 (Withdrawal) | F11: 净流动量 (Net Flow) | G11: 净流动状态 | I11: 通道 / 网络 | J11: 业务类型 | K11: 总订单数 | L11: 成功履约率 | M11: 异常/挂起率 | N11: 手续费创收 | P11: =DATE(2025, 7, 1) -> 45839 | Q11: =SUMIFS(fiat_transactions!$E$2:$E$26, fiat_transactions!$D$2:$D$26, "USD", fiat_transactions!$C$2:$C$26, "deposit", fiat_transactions!$H$2:$H$26, "completed", fiat_transactions!$I$2:$I$26, ">="&$P11, fiat_transactions!$I$2:$I$26, "<"&EDATE($P11, 1)) + SUMIFS(crypto_transactions!$F$2:$F$26, crypto_transactions!$D$2:$D$26, "USDT", crypto_transactions!$C$2:$C$26, "deposit", crypto_transactions!$J$2:$J$26, "completed", crypto_transactions!$L$2:$L$26, ">="&$P11, crypto_transactions!$L$2:$L$26, "<"&EDATE($P11, 1)) -> 0 | R11: =SUMIFS(fiat_transactions!$E$2:$E$26, fiat_transactions!$D$2:$D$26, "USD", fiat_transactions!$C$2:$C$26, "withdrawal", fiat_transactions!$H$2:$H$26, "completed", fiat_transactions!$I$2:$I$26, ">="&$P11, fiat_transactions!$I$2:$I$26, "<"&EDATE($P11, 1)) + SUMIFS(crypto_transactions!$F$2:$F$26, crypto_transactions!$D$2:$D$26, "USDT", crypto_transactions!$C$2:$C$26, "withdrawal", crypto_transactions!$J$2:$J$26, "completed", crypto_transactions!$L$2:$L$26, ">="&$P11, crypto_transactions!$L$2:$L$26, "<"&EDATE($P11, 1)) -> 0 | S11: =Q11-R11 -> 0
B12: USD | C12: 法币 (Fiat) | D12: =SUMIFS(fiat_transactions!$E$2:$E$26, fiat_transactions!$D$2:$D$26, "USD", fiat_transactions!$C$2:$C$26, "deposit", fiat_transactions!$H$2:$H$26, "completed") -> 76000 | E12: =SUMIFS(fiat_transactions!$E$2:$E$26, fiat_transactions!$D$2:$D$26, "USD", fiat_transactions!$C$2:$C$26, "withdrawal", fiat_transactions!$H$2:$H$26, "completed") -> 28270 | F12: =D12-E12 -> 47730 | G12: =IF(F12>0,"🟢 净流入",IF(F12=0,"⚪ 持平","🔴 净流出")) -> 🟢 净流入 | I12: wire_transfer | J12: 法币大额电汇 | K12: =COUNTIF(fiat_transactions!G2:G26, "wire_transfer") -> 6 | L12: =COUNTIFS(fiat_transactions!G2:G26, "wire_transfer", fiat_transactions!H2:H26, "completed") / K12 -> 0.83333333 | M12: =1 - L12 -> 0.16666667 | N12: =SUMIF(fiat_transactions!G2:G26, "wire_transfer", fiat_transactions!F2:F26) -> 120 | P12: =DATE(2025, 8, 1) -> 45870 | Q12: =SUMIFS(fiat_transactions!$E$2:$E$26, fiat_transactions!$D$2:$D$26, "USD", fiat_transactions!$C$2:$C$26, "deposit", fiat_transactions!$H$2:$H$26, "completed", fiat_transactions!$I$2:$I$26, ">="&$P12, fiat_transactions!$I$2:$I$26, "<"&EDATE($P12, 1)) + SUMIFS(crypto_transactions!$F$2:$F$26, crypto_transactions!$D$2:$D$26, "USDT", crypto_transactions!$C$2:$C$26, "deposit", crypto_transactions!$J$2:$J$26, "completed", crypto_transactions!$L$2:$L$26, ">="&$P12, crypto_transactions!$L$2:$L$26, "<"&EDATE($P12, 1)) -> 600 | R12: =SUMIFS(fiat_transactions!$E$2:$E$26, fiat_transactions!$D$2:$D$26, "USD", fiat_transactions!$C$2:$C$26, "withdrawal", fiat_transactions!$H$2:$H$26, "completed", fiat_transactions!$I$2:$I$26, ">="&$P12, fiat_transactions!$I$2:$I$26, "<"&EDATE($P12, 1)) + SUMIFS(crypto_transactions!$F$2:$F$26, crypto_transactions!$D$2:$D$26, "USDT", crypto_transactions!$C$2:$C$26, "withdrawal", crypto_transactions!$J$2:$J$26, "completed", crypto_transactions!$L$2:$L$26, ">="&$P12, crypto_transactions!$L$2:$L$26, "<"&EDATE($P12, 1)) -> 0 | S12: =Q12-R12 -> 600
B13: EUR | C13: 法币 (Fiat) | D13: =SUMIFS(fiat_transactions!$E$2:$E$26, fiat_transactions!$D$2:$D$26, "EUR", fiat_transactions!$C$2:$C$26, "deposit", fiat_transactions!$H$2:$H$26, "completed") -> 9500 | E13: =SUMIFS(fiat_transactions!$E$2:$E$26, fiat_transactions!$D$2:$D$26, "EUR", fiat_transactions!$C$2:$C$26, "withdrawal", fiat_transactions!$H$2:$H$26, "completed") -> 500 | F13: =D13-E13 -> 9000 | G13: =IF(F13>0,"🟢 净流入",IF(F13=0,"⚪ 持平","🔴 净流出")) -> 🟢 净流入 | I13: ach | J13: 法币小额清算 | K13: =COUNTIF(fiat_transactions!G2:G26, "ach") -> 5 | L13: =COUNTIFS(fiat_transactions!G2:G26, "ach", fiat_transactions!H2:H26, "completed") / K13 -> 0.8 | M13: =1 - L13 -> 0.2 | N13: =SUMIF(fiat_transactions!G2:G26, "ach", fiat_transactions!F2:F26) -> 7 | P13: =DATE(2025, 9, 1) -> 45901 | Q13: =SUMIFS(fiat_transactions!$E$2:$E$26, fiat_transactions!$D$2:$D$26, "USD", fiat_transactions!$C$2:$C$26, "deposit", fiat_transactions!$H$2:$H$26, "completed", fiat_transactions!$I$2:$I$26, ">="&$P13, fiat_transactions!$I$2:$I$26, "<"&EDATE($P13, 1)) + SUMIFS(crypto_transactions!$F$2:$F$26, crypto_transactions!$D$2:$D$26, "USDT", crypto_transactions!$C$2:$C$26, "deposit", crypto_transactions!$J$2:$J$26, "completed", crypto_transactions!$L$2:$L$26, ">="&$P13, crypto_transactions!$L$2:$L$26, "<"&EDATE($P13, 1)) -> 0 | R13: =SUMIFS(fiat_transactions!$E$2:$E$26, fiat_transactions!$D$2:$D$26, "USD", fiat_transactions!$C$2:$C$26, "withdrawal", fiat_transactions!$H$2:$H$26, "completed", fiat_transactions!$I$2:$I$26, ">="&$P13, fiat_transactions!$I$2:$I$26, "<"&EDATE($P13, 1)) + SUMIFS(crypto_transactions!$F$2:$F$26, crypto_transactions!$D$2:$D$26, "USDT", crypto_transactions!$C$2:$C$26, "withdrawal", crypto_transactions!$J$2:$J$26, "completed", crypto_transactions!$L$2:$L$26, ">="&$P13, crypto_transactions!$L$2:$L$26, "<"&EDATE($P13, 1)) -> 11100 | S13: =Q13-R13 -> -11100
B14: GBP | C14: 法币 (Fiat) | D14: =SUMIFS(fiat_transactions!$E$2:$E$26, fiat_transactions!$D$2:$D$26, "GBP", fiat_transactions!$C$2:$C$26, "deposit", fiat_transactions!$H$2:$H$26, "completed") -> 3000 | E14: =SUMIFS(fiat_transactions!$E$2:$E$26, fiat_transactions!$D$2:$D$26, "GBP", fiat_transactions!$C$2:$C$26, "withdrawal", fiat_transactions!$H$2:$H$26, "completed") -> 2000 | F14: =D14-E14 -> 1000 | G14: =IF(F14>0,"🟢 净流入",IF(F14=0,"⚪ 持平","🔴 净流出")) -> 🟢 净流入 | I14: sepa_instant | J14: 欧洲即时汇款 | K14: =COUNTIF(fiat_transactions!G2:G26, "sepa_instant") -> 4 | L14: =COUNTIFS(fiat_transactions!G2:G26, "sepa_instant", fiat_transactions!H2:H26, "completed") / K14 -> 0.75 | M14: =1 - L14 -> 0.25 | N14: =SUMIF(fiat_transactions!G2:G26, "sepa_instant", fiat_transactions!F2:F26) -> 3 | P14: =DATE(2025, 10, 1) -> 45931 | Q14: =SUMIFS(fiat_transactions!$E$2:$E$26, fiat_transactions!$D$2:$D$26, "USD", fiat_transactions!$C$2:$C$26, "deposit", fiat_transactions!$H$2:$H$26, "completed", fiat_transactions!$I$2:$I$26, ">="&$P14, fiat_transactions!$I$2:$I$26, "<"&EDATE($P14, 1)) + SUMIFS(crypto_transactions!$F$2:$F$26, crypto_transactions!$D$2:$D$26, "USDT", crypto_transactions!$C$2:$C$26, "deposit", crypto_transactions!$J$2:$J$26, "completed", crypto_transactions!$L$2:$L$26, ">="&$P14, crypto_transactions!$L$2:$L$26, "<"&EDATE($P14, 1)) -> 1000 | R14: =SUMIFS(fiat_transactions!$E$2:$E$26, fiat_transactions!$D$2:$D$26, "USD", fiat_transactions!$C$2:$C$26, "withdrawal", fiat_transactions!$H$2:$H$26, "completed", fiat_transactions!$I$2:$I$26, ">="&$P14, fiat_transactions!$I$2:$I$26, "<"&EDATE($P14, 1)) + SUMIFS(crypto_transactions!$F$2:$F$26, crypto_transactions!$D$2:$D$26, "USDT", crypto_transactions!$C$2:$C$26, "withdrawal", crypto_transactions!$J$2:$J$26, "completed", crypto_transactions!$L$2:$L$26, ">="&$P14, crypto_transactions!$L$2:$L$26, "<"&EDATE($P14, 1)) -> 20 | S14: =Q14-R14 -> 980
B15: BRL | C15: 法币 (Fiat) | D15: =SUMIFS(fiat_transactions!$E$2:$E$26, fiat_transactions!$D$2:$D$26, "BRL", fiat_transactions!$C$2:$C$26, "deposit", fiat_transactions!$H$2:$H$26, "completed") -> 2500 | E15: =SUMIFS(fiat_transactions!$E$2:$E$26, fiat_transactions!$D$2:$D$26, "BRL", fiat_transactions!$C$2:$C$26, "withdrawal", fiat_transactions!$H$2:$H$26, "completed") -> 2500 | F15: =D15-E15 -> 0 | G15: =IF(F15>0,"🟢 净流入",IF(F15=0,"⚪ 持平","🔴 净流出")) -> ⚪ 持平 | I15: faster_payments | J15: 英国极速到账 | K15: =COUNTIF(fiat_transactions!G2:G26, "faster_payments") -> 4 | L15: =COUNTIFS(fiat_transactions!G2:G26, "faster_payments", fiat_transactions!H2:H26, "completed") / K15 -> 0.75 | M15: =1 - L15 -> 0.25 | N15: =SUMIF(fiat_transactions!G2:G26, "faster_payments", fiat_transactions!F2:F26) -> 2 | P15: =DATE(2025, 11, 1) -> 45962 | Q15: =SUMIFS(fiat_transactions!$E$2:$E$26, fiat_transactions!$D$2:$D$26, "USD", fiat_transactions!$C$2:$C$26, "deposit", fiat_transactions!$H$2:$H$26, "completed", fiat_transactions!$I$2:$I$26, ">="&$P15, fiat_transactions!$I$2:$I$26, "<"&EDATE($P15, 1)) + SUMIFS(crypto_transactions!$F$2:$F$26, crypto_transactions!$D$2:$D$26, "USDT", crypto_transactions!$C$2:$C$26, "deposit", crypto_transactions!$J$2:$J$26, "completed", crypto_transactions!$L$2:$L$26, ">="&$P15, crypto_transactions!$L$2:$L$26, "<"&EDATE($P15, 1)) -> 0 | R15: =SUMIFS(fiat_transactions!$E$2:$E$26, fiat_transactions!$D$2:$D$26, "USD", fiat_transactions!$C$2:$C$26, "withdrawal", fiat_transactions!$H$2:$H$26, "completed", fiat_transactions!$I$2:$I$26, ">="&$P15, fiat_transactions!$I$2:$I$26, "<"&EDATE($P15, 1)) + SUMIFS(crypto_transactions!$F$2:$F$26, crypto_transactions!$D$2:$D$26, "USDT", crypto_transactions!$C$2:$C$26, "withdrawal", crypto_transactions!$J$2:$J$26, "completed", crypto_transactions!$L$2:$L$26, ">="&$P15, crypto_transactions!$L$2:$L$26, "<"&EDATE($P15, 1)) -> 300 | S15: =Q15-R15 -> -300
B16: TRY | C16: 法币 (Fiat) | D16: =SUMIFS(fiat_transactions!$E$2:$E$26, fiat_transactions!$D$2:$D$26, "TRY", fiat_transactions!$C$2:$C$26, "deposit", fiat_transactions!$H$2:$H$26, "completed") -> 15000 | E16: =SUMIFS(fiat_transactions!$E$2:$E$26, fiat_transactions!$D$2:$D$26, "TRY", fiat_transactions!$C$2:$C$26, "withdrawal", fiat_transactions!$H$2:$H$26, "completed") -> 6000 | F16: =D16-E16 -> 9000 | G16: =IF(F16>0,"🟢 净流入",IF(F16=0,"⚪ 持平","🔴 净流出")) -> 🟢 净流入 | I16: TRON | J16: 链上 TRC-20 | K16: =COUNTIF(crypto_transactions!E2:E26, "TRON") -> 11 | L16: =COUNTIFS(crypto_transactions!E2:E26, "TRON", crypto_transactions!J2:J26, "completed") / K16 -> 1 | M16: =1 - L16 -> 0 | N16: =SUMIF(crypto_transactions!E2:E26, "TRON", crypto_transactions!G2:G26) -> 4 | P16: =DATE(2025, 12, 1) -> 45992 | Q16: =SUMIFS(fiat_transactions!$E$2:$E$26, fiat_transactions!$D$2:$D$26, "USD", fiat_transactions!$C$2:$C$26, "deposit", fiat_transactions!$H$2:$H$26, "completed", fiat_transactions!$I$2:$I$26, ">="&$P16, fiat_transactions!$I$2:$I$26, "<"&EDATE($P16, 1)) + SUMIFS(crypto_transactions!$F$2:$F$26, crypto_transactions!$D$2:$D$26, "USDT", crypto_transactions!$C$2:$C$26, "deposit", crypto_transactions!$J$2:$J$26, "completed", crypto_transactions!$L$2:$L$26, ">="&$P16, crypto_transactions!$L$2:$L$26, "<"&EDATE($P16, 1)) -> 1000 | R16: =SUMIFS(fiat_transactions!$E$2:$E$26, fiat_transactions!$D$2:$D$26, "USD", fiat_transactions!$C$2:$C$26, "withdrawal", fiat_transactions!$H$2:$H$26, "completed", fiat_transactions!$I$2:$I$26, ">="&$P16, fiat_transactions!$I$2:$I$26, "<"&EDATE($P16, 1)) + SUMIFS(crypto_transactions!$F$2:$F$26, crypto_transactions!$D$2:$D$26, "USDT", crypto_transactions!$C$2:$C$26, "withdrawal", crypto_transactions!$J$2:$J$26, "completed", crypto_transactions!$L$2:$L$26, ">="&$P16, crypto_transactions!$L$2:$L$26, "<"&EDATE($P16, 1)) -> 1800 | S16: =Q16-R16 -> -800
B17: USDT | C17: 加密货币 (Crypto) | D17: =SUMIFS(crypto_transactions!$F$2:$F$26, crypto_transactions!$D$2:$D$26, "USDT", crypto_transactions!$C$2:$C$26, "deposit", crypto_transactions!$J$2:$J$26, "completed") -> 8000 | E17: =SUMIFS(crypto_transactions!$F$2:$F$26, crypto_transactions!$D$2:$D$26, "USDT", crypto_transactions!$C$2:$C$26, "withdrawal", crypto_transactions!$J$2:$J$26, "completed") -> 5000 | F17: =D17-E17 -> 3000 | G17: =IF(F17>0,"🟢 净流入",IF(F17=0,"⚪ 持平","🔴 净流出")) -> 🟢 净流入 | I17: ETHEREUM | J17: 以太坊 ERC-20 | K17: =COUNTIF(crypto_transactions!E2:E26, "ETHEREUM") -> 4 | L17: =COUNTIFS(crypto_transactions!E2:E26, "ETHEREUM", crypto_transactions!J2:J26, "completed") / K17 -> 1 | M17: =1 - L17 -> 0 | N17: =SUMIFS(crypto_transactions!G2:G26, crypto_transactions!E2:E26, "ETHEREUM", crypto_transactions!D2:D26, "USDT") -> 5
B18: BTC | C18: 加密货币 (Crypto) | D18: =SUMIFS(crypto_transactions!$F$2:$F$26, crypto_transactions!$D$2:$D$26, "BTC", crypto_transactions!$C$2:$C$26, "deposit", crypto_transactions!$J$2:$J$26, "completed") -> 0.081 | E18: =SUMIFS(crypto_transactions!$F$2:$F$26, crypto_transactions!$D$2:$D$26, "BTC", crypto_transactions!$C$2:$C$26, "withdrawal", crypto_transactions!$J$2:$J$26, "completed") -> 0.02 | F18: =D18-E18 -> 0.061 | G18: =IF(F18>0,"🟢 净流入",IF(F18=0,"⚪ 持平","🔴 净流出")) -> 🟢 净流入 | I18: BSC | J18: 币安智能链 BEP-20 | K18: =COUNTIF(crypto_transactions!E2:E26, "BSC") -> 4 | L18: =COUNTIFS(crypto_transactions!E2:E26, "BSC", crypto_transactions!J2:J26, "completed") / K18 -> 0.5 | M18: =1 - L18 -> 0.5 | N18: =SUMIF(crypto_transactions!E2:E26, "BSC", crypto_transactions!G2:G26) -> 1.6 | P18: 看板数据层 · 主流公链 USDT 资金流向分布 (Network USDT Distribution)
B19: ETH | C19: 加密货币 (Crypto) | D19: =SUMIFS(crypto_transactions!$F$2:$F$26, crypto_transactions!$D$2:$D$26, "ETH", crypto_transactions!$C$2:$C$26, "deposit", crypto_transactions!$J$2:$J$26, "completed") -> 0.6 | E19: =SUMIFS(crypto_transactions!$F$2:$F$26, crypto_transactions!$D$2:$D$26, "ETH", crypto_transactions!$C$2:$C$26, "withdrawal", crypto_transactions!$J$2:$J$26, "completed") -> 0.1 | F19: =D19-E19 -> 0.5 | G19: =IF(F19>0,"🟢 净流入",IF(F19=0,"⚪ 持平","🔴 净流出")) -> 🟢 净流入 | I19: ARBITRUM | J19: 以太坊 Layer-2 | K19: =COUNTIF(crypto_transactions!E2:E26, "ARBITRUM") -> 2 | L19: =COUNTIFS(crypto_transactions!E2:E26, "ARBITRUM", crypto_transactions!J2:J26, "completed") / K19 -> 0.5 | M19: =1 - L19 -> 0.5 | N19: =SUMIF(crypto_transactions!E2:E26, "ARBITRUM", crypto_transactions!G2:G26) -> 0.3 | P19: 公链网络 (Network) | Q19: 充值入金 (Deposit) | R19: 提现出金 (Withdrawal) | S19: 净沉淀量 (Net Flow)
P20: TRON | Q20: =SUMIFS(crypto_transactions!$F$2:$F$26, crypto_transactions!$E$2:$E$26, "TRON", crypto_transactions!$D$2:$D$26, "USDT", crypto_transactions!$C$2:$C$26, "deposit", crypto_transactions!$J$2:$J$26, "completed") -> 7000 | R20: =SUMIFS(crypto_transactions!$F$2:$F$26, crypto_transactions!$E$2:$E$26, "TRON", crypto_transactions!$D$2:$D$26, "USDT", crypto_transactions!$C$2:$C$26, "withdrawal", crypto_transactions!$J$2:$J$26, "completed") -> 3200 | S20: =Q20-R20 -> 3800
B21: 📈 月度资金出入与净沉淀趋势 (Monthly Flow & Net Retention Dynamics) | I21: 🌐 主流公链 USDT 流入与流出对比 (USDT Network Distribution & Net Flow) | P21: ETHEREUM | Q21: =SUMIFS(crypto_transactions!$F$2:$F$26, crypto_transactions!$E$2:$E$26, "ETHEREUM", crypto_transactions!$D$2:$D$26, "USDT", crypto_transactions!$C$2:$C$26, "deposit", crypto_transactions!$J$2:$J$26, "completed") -> 0 | R21: =SUMIFS(crypto_transactions!$F$2:$F$26, crypto_transactions!$E$2:$E$26, "ETHEREUM", crypto_transactions!$D$2:$D$26, "USDT", crypto_transactions!$C$2:$C$26, "withdrawal", crypto_transactions!$J$2:$J$26, "completed") -> 1500 | S21: =Q21-R21 -> -1500
P22: BSC | Q22: =SUMIFS(crypto_transactions!$F$2:$F$26, crypto_transactions!$E$2:$E$26, "BSC", crypto_transactions!$D$2:$D$26, "USDT", crypto_transactions!$C$2:$C$26, "deposit", crypto_transactions!$J$2:$J$26, "completed") -> 600 | R22: =SUMIFS(crypto_transactions!$F$2:$F$26, crypto_transactions!$E$2:$E$26, "BSC", crypto_transactions!$D$2:$D$26, "USDT", crypto_transactions!$C$2:$C$26, "withdrawal", crypto_transactions!$J$2:$J$26, "completed") -> 300 | S22: =Q22-R22 -> 300
P23: ARBITRUM | Q23: =SUMIFS(crypto_transactions!$F$2:$F$26, crypto_transactions!$E$2:$E$26, "ARBITRUM", crypto_transactions!$D$2:$D$26, "USDT", crypto_transactions!$C$2:$C$26, "deposit", crypto_transactions!$J$2:$J$26, "completed") -> 400 | R23: =SUMIFS(crypto_transactions!$F$2:$F$26, crypto_transactions!$E$2:$E$26, "ARBITRUM", crypto_transactions!$D$2:$D$26, "USDT", crypto_transactions!$C$2:$C$26, "withdrawal", crypto_transactions!$J$2:$J$26, "completed") -> 0 | S23: =Q23-R23 -> 400
P24: 合计 / Total | Q24: =SUM(Q20:Q23) -> 8000 | R24: =SUM(R20:R23) -> 5000 | S24: =SUM(S20:S23) -> 3000
B35: 🚨 核心合规与账户风控处置矩阵 (Compliance & AML Incident Matrix) | I35: ⚠️ 链上阻塞与清算挂起处置矩阵 (On-Chain & Clearing Exceptions Matrix)
B36: 风险等级 | C36: 涉案用户 | D36: 关联订单号 | E36: 涉及金额 | F36: 违规成因 / 诊断 | G36: 运营处置与跟进动作 | I36: 异常类型 | J36: 涉及网络/通道 | K36: 关联订单号 | L36: 涉及金额 | M36: 技术根因 / 诊断 | N36: 处置建议与恢复动作
B37: 🔴 严重拦截失效 | C37: Irene Jung | D37: fo_20250920_50284719 | E37: $800.00 USD | F37: 【冻结账户出金】用户处于 frozen 状态，ACH 仍放行 $800 出金 | G37: 立即冻结下游清算通道，排查网关拦截切面，追索未到账资金 | I37: 🟠 广播卡单 | J37: ARBITRUM | K37: co_20251220_90317464 | L37: 250.00 USDT | M37: 【TxHash 为空】提现 processing 且确认数 0 | N37: 核查 L2 节点 RPC 状态，执行重广播或人工退回冲正
B38: 🔴 严重拦截失效 | C38: Irene Jung | D38: fo_20251025_50284720 | E38: $20.00 USD | F38: 【二次渗透出金】同用户再次成功渗透出金 $20 | G38: 紧急注销该用户 API 密钥，升级前置拦截中间件与限额熔断 | I38: 🟡 确认中延迟 | J38: BSC | K38: co_20250801_69248133 | L38: 500.00 USDT | M38: 【确认数滞后】充值处于 confirming (5/15 确认) | N38: 持续监控 BSC 主网出块，达标后自动触发充值上账
B39: 🟡 准入合规排查 | C39: Jonas Weber | D39: 无在途订单 | E39: €0.00 EUR | F39: 【准入风控】KYC Level 0 挂起中 | G39: 限制账户充提与交易功能，催促用户提交实名认证材料以防死账 | I39: 🟡 大额电汇在途 | J39: wire_transfer | K39: fo_20250720_61590240 | L39: $10,000.00 USD | M39: 【Swift 结算在途】Bob Miller 大额电汇 pending | N39: 专人向结算行索取 MT103 凭证，核实推进资金入账
B40: 🟢 规则校验合规 | C40: 全局风控引擎 | D40: 17/17 QA Passed | E40: -- | F40: 【质检基线】全量交易与余额对账规则 100% 验证通过 | G40: 保持实时风控旁路监听，持续监控高频出金异动 | I40: 🔴 链上广播失败 | J40: BSC | K40: co_20251201_69248134 | L40: 300.00 USDT | M40: 【节点广播超时】提现订单 failed，TxHash 未生成 | N40: 执行资金解冻并返还用户主账户，提醒用户重新发起
